Workbook

Sheet Cars_dataset_sheet1
A1: Ad ID | B1: Car_Name | C1: Make | D1: Make Model | E1: Year | F1: KM_driven | G1: Price
A2: 1019823763 | B2: Toyota Corolla Altis 1.6 cc | C2: Toyota | D2: Toyota Corrolla Altis | E2: 2015 | F2: 130000 | G2: 4000000
A3: 1032353392 | B3: Mitsubishi mini cab urgent sale | C3: Mitsubishi | D3: Mitsubishi Minica | E3: 2012 | F3: 115000 | G3: 1150000
A4: 1035626806 | B4: Suzuki Every 2013 Model 2019 Registered Jet Black Single hand Use A+ C | C4: Suzuki | D4: Suzuki Every | E4: 2013 | F4: 120000 | G4: 1900000
A5: 1036683049 | B5: Mehran 2016 VXR original condition | C5: Suzuki | D5: Suzuki Mehran VXR | E5: 2016 | F5: 38500 | G5: 1180000
A6: 1036970933 | B6: Daihatsu Cuore 2004 | C6: Daihatsu | D6: Daihatsu Cuore | E6: 2004 | F6: 100000 | G6: 700000
A7: 1038612589 | B7: Mitsubishi Minica 2 door Japanese Car for sale | C7: Mitsubishi | D7: Mitsubishi Minica | E7: 2007 | F7: 133500 | G7: 1300000
A8: 1043285959 | B8: toyota corolla 2005 | C8: Toyota | D8: Toyota Corolla XLI | E8: 2005 | F8: 195000 | G8: 1750000
A9: 1043893641 | B9: chska party call na kra | C9: KIA | D9: KIA Classic | E9: 2005 | F9: 129049 | G9: 550000
A10: 1045295959 | B10: Suzuki Wagon R FA Package 2019 Model 2022 Fresh Import 17360 Km driven | C10: Suzuki | D10: Suzuki Wagon R | E10: 2019 | F10: 18360 | G10: 3500000
A11: 1045445134 | B11: Carry Daaba Minicap Mitsubishi | C11: Mitsubishi | D11: Mitsubishi Minica | E11: 2017 | F11: 170000 | G11: 1500000
A12: 1046475308 | B12: Kia Spectra 2001 1.5 Automatic. Customised price negotiable hai jaldi | C12: KIA | D12: KIA Spectra | E12: 2001 | F12: 50000 | G12: 1200000
A13: 1046608801 | B13: suzuki every turbo 5gair Exchange posibl with Honda&corola 03195517118 | C13: Suzuki | D13: Suzuki Every | E13: 2016 | F13: 123456 | G13: 1750000
... A498: 1076289664 | B498: Carry Bolin | C498: Suzuki | D498: Suzuki Bolan | E498: 2019 | F498: 12345 | G498: 1350000
A499: 1076304786 | B499: 3119111071 | C499: Suzuki | D499: Suzuki Bolan | E499: 2010 | F499: 70000 | G499: 850000
A500: 1076307705 | B500: Dihatshu Mira 2012/15 New Condition Exchange with Alto Vxr | C500: Daihatsu | D500: Daihatsu Mira | E500: 2015 | F500: 99000 | G500: 2300000
A501: 1076311882 | B501: Mehran VXR 2008 | C501: Suzuki | D501: Suzuki Mehran VXR | E501: 2008 | F501: 50000 | G501: 750000
A502: 1076312655 | B502: KIA PICANTO 1.0 AT | C502: KIA | D502: KIA Picanto | E502: 2021 | F502: 18500 | G502: 3150000
A503: 1076320957 | B503: City 2009 -Prosmatic | C503: Honda | D503: Honda City IVTEC | E503: 2009 | F503: 146000 | G503: 2200000
A504: 1076322359 | B504: Santro Club 2004 Urgent Sale | C504: Hyundai | D504: Hyundai Santro | E504: 2004 | F504: 99000 | G504: 650000
A505: 1076323992 | B505: Mira Package XSA3 Like a Brand New Car | C505: Daihatsu | D505: Daihatsu Mira | E505: 2019 | F505: 115000 | G505: 3550000
A506: 1076340262 | B506: Carolla Altis 1.6 | C506: Toyota | D506: Toyota Corrolla Altis | E506: 2017 | F506: 90000 | G506: 3900000
A507: 1076347671 | B507: KIA SPECTRA IN V GOOD CONDITION. (O3OO55O6699) | C507: KIA | D507: KIA Spectra | E507: 2002 | F507: 1234 | G507: 520000
A508: 1076356020 | B508: every 07/12 for sale or Xchang Toyota car | C508: Suzuki | D508: Suzuki Every | E508: 2012 | F508: 200000 | G508: 1260000
A509: 1076380433 | B509: suzuki Alto vxr | C509: Suzuki | D509: Suzuki Alto | E509: 2012 | F509: 143000 | G509: 1020000
A510: 1076380992 | B510: Altis 1.6 automatic 2020/2021 for sale | C510: Toyota | D510: Toyota Corrolla Altis | E510: 2020 | F510: 58000 | G510: 4400000
A511: 1076385717 | B511: Hyndai santro club 2003 | C511: Hyundai | D511: Hyundai Santro | E511: 2003 | F511: 5555 | G511: 780000
... A730: 1077566598 | B730: 1.5 Honda City Aspire in Brand New Condition | C730: Honda | D730: Honda City Aspire | E730: 2017 | F730: 51000 | G730: 3250000
A731: 1077567793 | B731: 3002195137 | C731: Suzuki | D731: Suzuki Bolan | E731: 2017 | F731: 62000 | G731: 1150000
A732: 1077572197 | B732: Mitsubishi Lancer 2005 model in good condition | C732: Mitsubishi | D732: Mitsubishi Lancer | E732: 2005 | F732: 70000 | G732: 1370000
A733: 1077576628 | B733: dihatsu move urgent sale | C733: Daihatsu | D733: Daihatsu Move | E733: 2021 | F733: 100000 | G733: 2900000
A734: 1077577910 | B734: honda city 2010 | C734: Honda | D734: Honda City IVTEC | E734: 2010 | F734: 145000 | G734: 2500000
A735: 1077578497 | B735: Honda civic reborn | C735: Honda | D735: Honda Civic Prosmetic | E735: 2009 | F735: 97000 | G735: 1800000
A736: 1077580298 | B736: Cuore 2012 | C736: Daihatsu | D736: Daihatsu Cuore | E736: 2012 | F736: 120000 | G736: 865000
A737: 1077583006 | B737: honda city 1.3 Mt | C737: Honda | D737: Honda City IVTEC | E737: 2019 | F737: 58000 | G737: 3500000
A738: 1077583460 | B738: Ek Wagon 2008/2013 [660cc] | C738: Mitsubishi | D738: Mitsubishi Ek Wagon | E738: 2008 | F738: 140000 | G738: 1700000
A739: 1077592008 | B739: Mercedes C 200 Kompressor | C739: Mercedes | D739: Mercedes C Class | E739: 2003 | F739: 200000 | G739: 2300000
A740: 1077609801 | B740: i am selling my lancer glx 1.5 automatic | C740: Mitsubishi | D740: Mitsubishi Lancer | E740: 2006 | F740: 65000 | G740: 1550000
A741: 1077612923 | B741: Mira model 2014 registration 2017 | C741: Daihatsu | D741: Daihatsu Mira | E741: 2014 | F741: 119000 | G741: 2460000
A742: 1077614644 | B742: Honda City IDSI Vario | C742: Honda | D742: Honda City Vario | E742: 2007 | F742: 79000 | G742: 1680000
A743: 1077617252 | B743: sentro Hyundai | C743: Hyundai | D743: Hyundai Santro | E743: 2006 | F743: 17000 | G743: 849999
... A747: 1077637008 | B747: Suzuki every 7/12/15 | C747: Suzuki | D747: Suzuki Every | E747: 2015 | F747: 140000 | G747: 1185000
A748: 1077647354 | B748: 3086863882 | C748: Honda | D748: Honda City Vario | E748: 2006 | F748: 170000 | G748: 1770000
A749: 1077651584 | B749: Daihatsu tarios 2011 full option | C749: Daihatsu | D749: Daihatsu Terios Kid | E749: 2011 | F749: 250000 | G749: 4000000
A750: 1077660847 | B750: Wagon R 2018 Full Perfect Never Open 0 Accident | C750: Suzuki | D750: Suzuki Wagon R | E750: 2018 | F750: 93575 | G750: 1925000
A751: 1077674292 | B751: Honda civic Rebirth | C751: Honda | D751: Honda Civic Oriel | E751: 2013 | F751: 140000 | G751: 3280000
A752: 1077674415 | B752: Mercedes C180 2008 model Islamabad registered | C752: Mercedes | D752: Mercedes C Class | E752: 2008 | F752: 117000 | G752: 4900000
A753: 1077676902 | B753: Mira 2011-15 | C753: Daihatsu | D753: Daihatsu Mira | E753: 2011 | F753: 100000 | G753: 2050000
A754: 1077679088 | B754: suzuki cultus for sale | C754: Suzuki | D754: Suzuki Cultus VXR | E754: 2001 | F754: 150000 | G754: 570000
A755: 1077687947 | B755: Suzuki Every fully loaded For Sale | C755: Suzuki | D755: Suzuki Every | E755: 2016 | F755: 59000 | G755: 2390000
A756: 1077690189 | B756: I'm selling my swift car in good condition not a single work required. | C756: Suzuki | D756: Suzuki Swift | E756: 2017 | F756: 79000 | G756: 2400000
A757: 1077693334 | B757: Toyota altis grande 2018 | C757: Toyota | D757: Toyota Altis Grande | E757: 2018 | F757: 99850 | G757: 5000000
A758: 1077694829 | B758: Toyota pixis | C758: Daihatsu | D758: Daihatsu Mira | E758: 2015 | F758: 89000 | G758: 2230000
A759: 1077700845 | B759: Honda city Almost Geniun for sale | C759: Honda | D759: Honda City IDSI | E759: 2005 | F759: 200000 | G759: 1550000
A760: 1077708945 | B760: Toyota Passo | C760: Toyota | D760: Toyota Passo | E760: 2013 | F760: 135000 | G760: 2475000
... A1014: 1078384970 | B1014: passo 2013 model reg 2017 | C1014: Toyota | D1014: Toyota Passo | E1014: 2013 | F1014: 96000 | G1014: 2725000
A1015: 1078387916 | B1015: 45575 | C1015: Honda | D1015: Honda City Aspire | E1015: 2013 | F1015: 106500 | G1015: 2700000
A1016: 1078391403 | B1016: Special Suzuki Every Wagon for sale in low price. | C1016: Suzuki | D1016: Suzuki Every | E1016: 2010 | F1016: 200000 | G1016: 2500000
A1017: 1078400918 | B1017: Suzuki every Hijet clipper | C1017: Suzuki | D1017: Suzuki Every | E1017: 2016 | F1017: 108888 | G1017: 1365000
A1018: 1078403773 | B1018: Honda city 2007 silver original condition | C1018: Honda | D1018: Honda City IDSI | E1018: 2007 | F1018: 12345 | G1018: 1575000
A1019: 1078407463 | B1019: Alto 2020 VXR | C1019: Suzuki | D1019: Suzuki Alto | E1019: 2020 | F1019: 65000 | G1019: 2290000
A1020: 1078407721 | B1020: Suzuki Mehran VXR 2017/18 | C1020: Suzuki | D1020: Suzuki Mehran VXR | E1020: 2017 | F1020: 45000 | G1020: 1299000
A1021: 1078407880 | B1021: Selling my Daihatsu Terios Kid | C1021: Daihatsu | D1021: Daihatsu Terios Kid | E1021: 2008 | F1021: 150000 | G1021: 1680000
A1022: 1078408201 | B1022: WAGONR VXL 2021 | C1022: Suzuki | D1022: Suzuki Wagon R | E1022: 2021 | F1022: 45000 | G1022: 2490000
A1023: 1078409586 | B1023: cultus 2006 for sale | C1023: Suzuki | D1023: Suzuki Cultus VXR | E1023: 2006 | F1023: 70374 | G1023: 750000
A1024: 1078412721 | B1024: Toyota Corolla XLI 2010/11 urgently sale | C1024: Toyota | D1024: Toyota Corolla XLI | E1024: 2011 | F1024: 110325 | G1024: 1890000
A1025: 1078413809 | B1025: Baleno silver. 2005 | C1025: Suzuki | D1025: Suzuki Baleno | E1025: 2005 | F1025: 290000 | G1025: 910000
A1026: 1078418976 | B1026: Daihatsu Hijet 2013 | C1026: Daihatsu | D1026: Daihatsu Hijet | E1026: 2013 | F1026: 50000 | G1026: 1450000
A1027: 1078420313 | B1027: Hyundai santro 2007 | C1027: Hyundai | D1027: Hyundai Santro | E1027: 2007 | F1027: 148000 | G1027: 1060000
... A1088: 1078555589 | B1088: Sentro Club (New Engine) | C1088: Hyundai | D1088: Hyundai Santro | E1088: 2005 | F1088: 1000 | G1088: 1040000
A1089: 1078557043 | B1089: 3226934100 | C1089: Daihatsu | D1089: Daihatsu Move | E1089: 2018 | F1089: 130000 | G1089: 2390000
A1090: 1078562919 | B1090: Toyota Passo 2014/2016 | C1090: Toyota | D1090: Toyota Passo | E1090: 2014 | F1090: 69000 | G1090: 2530000
A1091: 1078563475 | B1091: Suzuki Mahran | C1091: Suzuki | D1091: Suzuki Mehran VXR | E1091: 2007 | F1091: 82820 | G1091: 700000
A1092: 1078563817 | B1092: gli 2017/18 white totally genuine except one and half door | C1092: Toyota | D1092: Toyota Corolla GLI | E1092: 2018 | F1092: 95000 | G1092: 3995000
A1093: 1078565376 | B1093: Suzuki Ravi 2007 | C1093: Suzuki | D1093: Suzuki Ravi | E1093: 2007 | F1093: 40000 | G1093: 700000
A1094: 1078578893 | B1094: final price | C1094: Suzuki | D1094: Suzuki Swift | E1094: 2020 | F1094: 75000 | G1094: 2450000
A1095: 1078580569 | B1095: Suzuki Wagonr vxl 2018 | C1095: Suzuki | D1095: Suzuki Wagon R | E1095: 2018 | F1095: 68000 | G1095: 1925000
A1096: 1078582101 | B1096: suzuki baleno jxr | C1096: Suzuki | D1096: Suzuki Baleno | E1096: 2004 | F1096: 12345 | G1096: 1500000
A1097: 1078585555 | B1097: 2021 kia picanto low milage the pictures provided are genuine. | C1097: KIA | D1097: KIA Picanto | E1097: 2021 | F1097: 23000 | G1097: 2800000
A1098: 1078586269 | B1098: Yaris | C1098: Toyota | D1098: Toyota Yaris | E1098: 2021 | F1098: 40000 | G1098: 4600000
A1099: 1078587840 | B1099: corolla GLI 2020 | C1099: Toyota | D1099: Toyota Corolla GLI | E1099: 2020 | F1099: 140000 | G1099: 4500000
A1100: 1078594006 | B1100: terios kid | C1100: Daihatsu | D1100: Daihatsu Terios Kid | E1100: 2004 | F1100: 123123 | G1100: 1425000
A1101: 1078594500 | B1101: Honda Civic 2016Model Oriel | C1101: Honda | D1101: Honda Civic Oriel | E1101: 2016 | F1101: 116000 | G1101: 4550000
... A1597: 1079292907 | B1597: KIA Picanto | C1597: KIA | D1597: KIA Picanto | E1597: 2021 | F1597: 43000 | G1597: 2975000
A1598: 1079293060 | B1598: 3344040213 | C1598: Toyota | D1598: Toyota Corolla XLI | E1598: 2005 | F1598: 195000 | G1598: 1350000
A1599: 1079293250 | B1599: Mehran VXR 2019 | C1599: Suzuki | D1599: Suzuki Mehran VXR | E1599: 2019 | F1599: 47000 | G1599: 1850000
A1600: 1079294931 | B1600: Mehran car vxr 2012 | C1600: Suzuki | D1600: Suzuki Mehran VXR | E1600: 2012 | F1600: 190000 | G1600: 620000
A1601: 1079294962 | B1601: urgent sale Wagnor vxl 2018 | C1601: Suzuki | D1601: Suzuki Wagon R | E1601: 2018 | F1601: 66000 | G1601: 2150000
A1602: 1079295542 | B1602: Lahore Number Gari ki condition bht achi ha Drive smooth AC Chill | C1602: Mitsubishi | D1602: Mitsubishi Lancer | E1602: 2005 | F1602: 180000 | G1602: 1220000
A1603: 1079296103 | B1603: Suzuki Mehran Vxr | C1603: Suzuki | D1603: Suzuki Mehran VXR | E1603: 2017 | F1603: 86000 | G1603: 1315000
A1604: 1079296505 | B1604: mehran vxr 2017 model. genuine car no shower | C1604: Suzuki | D1604: Suzuki Mehran VXR | E1604: 2017 | F1604: 85000 | G1604: 1200000
A1605: 1079298574 | B1605: Honda City Aspire 1.5 New Shape Isb Reg. (2022) | C1605: Honda | D1605: Honda City Aspire | E1605: 2021 | F1605: 25000 | G1605: 5000000
A1606: 1079299769 | B1606: suzuki bolan kohat. whattsapp plz | C1606: Suzuki | D1606: Suzuki Bolan | E1606: 2021 | F1606: 30000 | G1606: 1920000
A1607: 1079304641 | B1607: Mercedes E200 2003/2006 | C1607: Mercedes | D1607: Mercedes E Class | E1607: 2003 | F1607: 107000 | G1607: 4500000
A1608: 1079305170 | B1608: Toyota Corolla GLi Automatic 1.3 VVTi | C1608: Toyota | D1608: Toyota Corolla GLI | E1608: 2017 | F1608: 111000 | G1608: 4100000
A1609: 1079307483 | B1609: Daihatsu Mira 2012 | C1609: Daihatsu | D1609: Daihatsu Mira | E1609: 2012 | F1609: 45000 | G1609: 800000
A1610: 1079307682 | B1610: 2015 import | C1610: Suzuki | D1610: Suzuki Wagon R | E1610: 2015 | F1610: 85000 | G1610: 2300000
... A1658: 1079343718 | B1658: Toyota Corolla xli total genuine Karachi registered ( 033319 47927 ) | C1658: Toyota | D1658: Toyota Corolla XLI | E1658: 2015 | F1658: 148537 | G1658: 2960000
A1659: 1079344053 | B1659: 3000664041 | C1659: Hyundai | D1659: Hyundai Santro | E1659: 2000 | F1659: 190000 | G1659: 600000
A1660: 1079344400 | B1660: City 2001 Manual transmission | C1660: Honda | D1660: Honda City IDSI | E1660: 2001 | F1660: 217443 | G1660: 850000
...

Sheet Cars_dataset_sheet2
A1: Ad ID | B1: Fuel | C1: Registration_city | D1: Car_documents | E1: Seller_Location | F1: Description | G1: Assembly | H1: Transmission | I1: Condition
A2: 1080762189 | B2: Petrol | C2: Karachi | D2: Original | E2: Awan Town, Lahore | F2: I m selling my swift car, very good condition total janiun. Like New car. First hand used only driven 65000 I m second owner. Price almost final but slightly negushiat. Home used car. Just buy and drive. Serious buyer just text. No call | G2: Local | H2: Manual | I2: Used
A3: 1080784426 | B3: Petrol | C3: Lahore | D3: Original | E3: DHA Defence, Karachi | F3: Suzuki Swift 1.3 DLX 2014 Model. 2nd Owner. 40000kms Driven. Sparingly Used. Entirely Genuine and Scratch Less. . Throughout Petrol Driven. Expensive Rims and new Tires installed recently. Leather Seats. New Battery. Absolutely no work required. Buy and Drive. All Documents Complete. Taxes upto Date. Calls only | G3: Local | H3: Manual | I3: Used
A4: 1060740152 | B4: Petrol | C4: Lahore | D4: Original | E4: Bahria Town Phase 8, Rawalpindi | F4: Suzuki marhan 2017 model | G4: Local | H4: Manual | I4: Used
A5: 1063029544 | B5: Petrol | C5: Karachi | D5: Original | E5: Royal 8 Icon, Karachi | F5: URGENT CASH NEEDED. AUTO coverted installed with 1500cc EFI japanese engine,( Not updated on book). Car is in excellent working condition new suspension and steering system installed for good maneuvering and smooth drive, installed with working AC, power windows and power steering, android system and speakers also installed. all oils changed. soundless and water dropping engine. only tikli is missing. showered from outside. undercoat is done with european standard paint. no rust on the body. tax is around 27,000 and will be paid by the buyer on finalization of deal. documents are complete only the first 2 books are missing but current book is available. contact on whatsapp if number not being received please. Reason for selling is it is in excess at home | G5: Local | H5: Automatic | I5: Used
A6: 1068252730 | B6: Petrol | C6: Lahore | D6: Original | E6: Aziz Bhatti Shaheed Road, Sialkot | F6: honda city total orgnall family use urgent sale and exchange auto car | G6: Local | H6: Manual | I6: Used
A7: 1068494302 | B7: Petrol | C7: Lahore | D7: Original | E7: Aziz Bhatti Shaheed Road, Sialkot | F7: honda city somth new condition family use orgnall urgent sale and exchange auto | G7: Local | H7: Manual | I7: Used
A8: 1068567690 | B8: Petrol | C8: Karachi | D8: Original | E8: Gulshan-e-Iqbal, Karachi | F8: 1st owner fully maintained smells like new full original water dropping engine | G8: Local | H8: Automatic | I8: Used
A9: 1070497471 | B9: Petrol | C9: Karachi | D9: Original | E9: DHA Defence, Karachi | F9: Honda City prosmatic 1.3 low mileage original bumper to Bumper just like new. model 2018 November 2nd owner in my name. New Yokohama blue earth tyres | G9: Local | H9: Automatic | I9: Used
A10: 1072822149 | B10: Petrol | C10: Karachi | D10: Original | E10: Allahwala Town, Karachi | F10: Yaris 2023 Gli Manual 1.3 silver Colour price full and final hayn | G10: Local | H10: Manual | I10: Used
A11: 1073368879 | B11: Petrol | C11: Faisalabad | D11: Original | E11: Faisalabad, Punjab | F11: Baher say Sara paint hai or documents original hai. | G11: Local | H11: Manual | I11: Used
A12: 1074728073 | B12: Petrol | C12: Karachi | D12: Original | E12: Nazimabad 1, Karachi | F12: my car is sale good condition LCD back camera power starting power window all documents clear original CPLC killer only home use car all system working Koi Kam Nahin hai bus lo chalao new tyre only call no message barai meherbani only call | G12: Local | H12: Manual | I12: Used
A13: 1075945797 | B13: Petrol | C13: Lahore | D13: Original | E13: Depalpur Road, Okara | F13: bolan cary daba purches date 2019 model | G13: Imported | H13: Manual | I13: Used
... A406: 1072408950 | B406: Petrol | C406: Faisalabad | D406: Original | E406: Faisalabad, Punjab | F406: Minor tuchup room total janwan fresh look dacoments clear bayometrc on spot | G406: Local | H406: Manual | I406: Used
A407: 1072411638 | B407: Petrol | C407: Sindh | D407: Original | E407: Airport Enclave, Islamabad | F407: 3345154198 | G407: Imported | H407: Manual | I407: Used
A408: 1072423579 | B408: Petrol | C408: Islamabad | D408: Original | E408: Palm City, Rawalpindi | F408: Selling Toyota Passo 2007 Model 2012 Import Engine Capicity at 70-75%. All in Original Color. Only Bumpers are painted. REST OF THE BODY IS IN ORIGINAL CONDITION. | G408: Imported | H408: Automatic | I408: Used
A409: 1072423748 | B409: Petrol | C409: Punjab | D409: Original | E409: Canal View, Lahore | F409: AoA. i want to sell my total genuine, scratchless, neat and clean car. Car in in my own name. Its drive is just like new car. Price is almost final, Only serious buyers may contact. Leather poshish and LCD installed. | G409: Local | H409: Manual | I409: Used
A410: 1072502304 | B410: Petrol | C410: Lahore | D410: Original | E410: Mushtaq Colony, Lahore | F410: I am a selling a 2 door Mitsubishi Manica car. 16-18KM/L. Ac is perfect ok , suspension perfect smart card and original documents are available. if you want to buy just text me. or call me on | G410: Imported | H410: Automatic | I410: Used
A411: 1072606415 | B411: Petrol | C411: Gujranwala | D411: Original | E411: Safdar Abad, SheikhÃ¼pura | F411: Alloy Rim good condition back cemra LCD mp3 player instaled just buy and drive no work required all original documents available | G411: Local | H411: Manual | I411: Used
A412: 1072657831 | B412: Petrol | C412: Karachi | D412: Original | E412: Soan Garden, Islamabad | F412: Toyota Altis 2016 Very good condition. No work is required at all. Almost 89000 km driven with good care like a girlfriend only One piece touch-up. Come with your mechanic and Denter. Recently done routine check-ups with Toyota Creek, bills are available for your satisfaction. Transmission Oil and engine oil were changed at 89000 KM through the Toyota Creek bills are also available for your satisfaction. The price of the car is final and there will be no change so please call if you agree with this amount otherwise don't call | G412: Local | H412: Automatic | I412: Used
A413: 1072671849 | B413: Petrol | C413: Lahore | D413: Original | E413: Madina Town, Faisalabad | F413: Daihatsu mira es All documents available biometric available Brighstone new tires with spare tire Light weight alloy rims installed Family used car LCD panel installed 4.5 grade car from Japan non accident car WhatsApp number= | G413: Imported | H413: Automatic | I413: Used
A414: 1072673258 | B414: Petrol | C414: Multan | D414: Original | E414: Others, Arifwala | F414: Suzuki Cultus VXR 2006 no work required smooth drive bio availiable 2nd onwer body 90% ok inter geniune price already negotiate serious buyer contact me no foolish offer only call | G414: Imported | H414: Manual | I414: Used
A415: 1072797519 | B415: Petrol | C415: Karachi | D415: Original | E415: Kohsar, Hyderabad | F415: engine 10/10 tyre 10/10 original bumper to bumper genuine family used car tax upto date Ac chilled sound system ju lega woh transfer krwaye ga apny nam pe | G415: Imported | H415: Manual | I415: Used
A416: 1072845373 | B416: Petrol | C416: Lahore | D416: Original | E416: Yaqoob Abad, Burewala | F416: I am sale car Suzuki Khyber engine modified mira daihtsu 660 cc good petrol average chil Ac original phle car chq kry phir rate ki bat kry | G416: Imported | H416: Automatic | I416: Used
A417: 1072911802 | B417: Petrol | C417: Islamabad | D417: Original | E417: I-8 Markaz, Islamabad | F417: Suzuki Mehran 2015 VXR mechanically perfect new tyres complete documents lifetime tokens paid Price slightly negotiable | G417: Local | H417: Manual | I417: Used
A418: 1072936521 | B418: Petrol | C418: Lahore | D418: Original | E418: Jhang City, Jhang | F418: Car is total genuine condition . One hand Home Used Family car . no denting no painting. Biomatric also available . No work required just buy and drive . Gift for toyota lover . 68000 milage only. Fresh car . 13+ average Alhamdulillah. | G418: Local | H418: Automatic | I418: Used
A419: 1072976575 | B419: Petrol | C419: Lahore | D419: Original | E419: Mehrpura Sharqi, Attock | F419: Suzuki mehran all ok carry daba Kay Sath matcha ho saka hai up model ho | G419: Local | H419: Manual | I419: Used
... A2002: 1079544325 | B2002: Petrol | C2002: Karachi | D2002: Original | E2002: Gulistan-e-Jauhar, Karachi | F2002: 1st owner no touchups no shower full genuine paint spare key unused all user manual available one hand driven only serious buyers can call | G2002: Local | H2002: Automatic | I2002: Used
A2003: 1079544851 | B2003: Petrol | C2003: Karachi | D2003: Original | E2003: Allama Iqbal Town, Lahore | F2003: #NAME? | G2003: Local | H2003: Manual | I2003: Used
A2004: 1079544992 | B2004: Petrol | C2004: Lahore | D2004: Original | E2004: GT Road, Muridike | F2004: honda city 2010 1.3 manual mint condition engine 10/10 Non accident body condition 9/10 total genuine except diggii alloy rims interior used 9.5/10 Mostly used in home suspension 9/10 WhatsApp for visiting! thanks in advance. | G2004: Local | H2004: Manual | I2004: Used
A2005: 1079545075 | B2005: Petrol | C2005: Karachi | D2005: Original | E2005: DHA Phase 2 Extension, Karachi | F2005: MAKE TOYOTA COROLLA VARIENT ALTIS 1.6 MODEL 2015 REG 2015 COLOUR SUPER WHITE BODY TOTAL ORIGINAL MILEAGE 73000km (NOTE) :- Toyota Corolla Altis 1.6 IMMACULATE CONDITION, TOTAL ORIGINAL NEW TYRES,Everything 100% | G2005: Local | H2005: Automatic | I2005: Used
A2006: 1079547680 | B2006: Petrol | C2006: Lahore | D2006: Original | E2006: Others, Khanewal | F2006: City b2b genuine 1.3 manual. b2b means b2b. white colour price is slightly negotiable. Only serious person should contact. Car is in kabirwala | G2006: Local | H2006: Manual | I2006: Used
A2007: 1079550264 | B2007: Petrol | C2007: Islamabad | D2007: Original | E2007: B-17, Islamabad | F2007: Toyota passo Hana plus Limited edition Top variant. Full options Sofa seat . Climate control AC Model 2012 Islamabad number Full genuine. No touching. No paint. No spray. Seal by seal. Projected light Original smart card on my own name. Fresh biometric available. Red wine colour Keyless entry. New tyre. Engine water throwing. Fuel average On long 18 On local 16 average. Army Officer used car proof available Car can be seen at sector B-17 Multigarden Islamabad anytime. | G2007: Imported | H2007: Automatic | I2007: Used
A2008: 1079550726 | B2008: Petrol | C2008: Karachi | D2008: Original | E2008: Nazimabad, Karachi | F2008: Selling my Honda city aspire manual transmission side tochups some due to scratch inner genuine neat and clean car first owner Android installed new battery new tyres installed recently each and every thing clear can I kept with care as seen in pics interested just call here | G2008: Local | H2008: Manual | I2008: Used
A2009: 1079552812 | B2009: Petrol | C2009: Karachi | D2009: Original | E2009: PECHS, Karachi | F2009: cultus 2014 registerd 2015 family used car jus buy and drive pechs block 6 0346/233/5231 timing 9 to 6 | G2009: Local | H2009: Manual | I2009: Used
A2010: 1079560221 | B2010: Petrol | C2010: Rawalpindi | D2010: Original | E2010: Mian Khel Bazar, Kohat | F2010: Ø§Ú†Ú¾ÛŒ Ú©Ù†ÚˆÛŒØ´Ù† Û”ØµØ§Ù Ø³ØªÚ¾Ø±ÛŒ Ú¯Ø§Ú‘ÛŒ Û”Ú¯Ú¾Ø± Ú©Û’ Ø§Ø³ØªØ¹Ù…Ø§Ù„ Ú©ÛŒ Û”Ú©ÙˆØ¦ÛŒ Ú©Ø§Ù… Ù†ÛÛŒÚº Û”Ø®Ø±ÛŒØ¯ÛŒÚº Ø§ÙˆØ± Ú†Ù„Ø§Ø¦ÛŒÚº Û” | G2010: Imported | H2010: Automatic | I2010: Used
A2011: 1079560608 | B2011: Petrol | C2011: Lahore | D2011: Original | E2011: Shadman 2, Karachi | F2011: Suzuki bolan petrosal cng suspension perfect brand new tyre with alarm install sound system ok interior neat and clean location nagan choring contact number zero Three dubal One two zero six Three dubal two nine | G2011: Local | H2011: Manual | I2011: Used
A2012: 1079561776 | B2012: Petrol | C2012: Lahore | D2012: Original | E2012: Scheme 33 - Sector 18-A, Karachi | F2012: A. Salam I am selling my Honda city 2017/18 in mint condition. Car ma 1 minor sa touch up hai scratches hai thora bohat. Everything is excellent just buy and drive urgent sell karni hai I am not a broker so broker wala rate nahi lagana 33 lakh sa kaam wala call nahi kara serious buyer contact kara Thank you | G2012: Local | H2012: Automatic | I2012: Used
A2013: 1079562921 | B2013: Petrol | C2013: Multan | D2013: Original | E2013: Chungi No. 5, Kabirwala | F2013: new condition dual ac fog lights (no work required) new tires no teaching please serious people contact me | G2013: Imported | H2013: Manual | I2013: Used
A2014: 1079563213 | B2014: Petrol | C2014: Sindh | D2014: Original | E2014: Sardargarhi, Peshawar | F2014: Kia sportage 2002 madal karchi nambar 2000cc petrol engine and double cylinder cng One my name Smart card available file and hand Spray on outside, genuine on inside New tire and new rim Alarm W N (O321)9O\6O\634\ | G2014: Imported | H2014: Manual | I2014: Used
A2015: 1079565467 | B2015: Petrol | C2015: Islamabad | D2015: Original | E2015: Peshawar Road, Rawalpindi | F2015: Seeing is believing! Immaculate Toyota Corolla GLI 2019 Key Features: Excellent Condition Low Mileage, Family-Used Car Genuine Suspension and Engine Condition Plastic Floor Matting Since Purchase Regular Maintenance at Authorized Workshop Complete Accessories including Top Cover and Extra Keys Equipped with Brand New Daewoo Dry Battery under Warranty Token Paid Till June 2024 Price is Firm, No Room for Negotiation Serious Buyers Only, No Unreasonable Offers 100% Original, Meticulously Maintained, Just Like a Zero Meter Car | G2015: Local | H2015: Automatic | I2015: Used
... A3233: 1080270853 | B3233: Petrol | C3233: Karachi | D3233: Original | E3233: State Life Housing Phase 1, Lahore | F3233: original automatic coure car | G3233: Imported | H3233: Automatic | I3233: Used
A3234: 1080271128 | B3234: Petrol | C3234: Multan | D3234: Original | E3234: Others, Depalpur | F3234: 1 | G3234: Local | H3234: Manual | I3234: Used
A3235: 1080271347 | B3235: Petrol | C3235: Faisalabad | D3235: Original | E3235: Jaranwala, Faisalabad | F3235: Book file jenion Baio metriq moqey py. . . . . new tair location zilla okara mey. . . | G3235: Local | H3235: Manual | I3235: Used
A3236: 1080271782 | B3236: Petrol | C3236: Karachi | D3236: Original | E3236: Cantt, Quetta | F3236: Toyota Passo | G3236: Imported | H3236: Automatic | I3236: Used
A3237: 1080272134 | B3237: Petrol | C3237: Lahore | D3237: Original | E3237: Kassowal, Chichawatni | F3237: fast sale xli k sath x change ho skte hai price final hai | G3237: Imported | H3237: Manual | I3237: Used
A3238: 1080272294 | B3238: Petrol | C3238: Punjab | D3238: Original | E3238: Daska Road, Sialkot | F3238: bumper tou bumper junine brand new car engine 100% suspion % lush condition All documents clear bio matric available | G3238: Imported | H3238: Manual | I3238: Used
A3239: 1080272401 | B3239: Petrol | C3239: Karachi | D3239: Original | E3239: New Hyderabad City, Hyderabad | F3239: mira 2019/2022 in new shape no any work required just buy and drive as like new one. | G3239: Imported | H3239: Automatic | I3239: Used
A3240: 1080272477 | B3240: Petrol | C3240: Lahore | D3240: Original | E3240: Allama Iqbal Town, Lahore | F3240: Daihatsu move 2012/14 model engine n suspension and ac 100% very smooth drive neat n clean car 18 say 26 tk average car is my own name Air bags packed | G3240: Imported | H3240: Automatic | I3240: Used
A3241: 1080272636 | B3241: Petrol | C3241: Lahore | D3241: Original | E3241: Chak 208 Road, Faisalabad | F3241: excellent condition power starring new tyre no work require home use water throwing engine petrol and ganinion cng fitted from company with 4 baby cylinder . only serious customer contact | G3241: Imported | H3241: Manual | I3241: Used
A3242: 1080272793 | B3242: Petrol | C3242: Karachi | D3242: Original | E3242: Scheme 33, Karachi | F3242: honda city 2014 automatic | G3242: Local | H3242: Automatic | I3242: Used
A3243: 1080272839 | B3243: Petrol | C3243: Karachi | D3243: Original | E3243: Gulistan-e-Jauhar Block 3, Karachi | F3243: outside shower inside original documents clear cplc clear own engine on petrol engine 100% AC on | G3243: Local | H3243: Manual | I3243: Used
A3244: 1080272864 | B3244: Petrol | C3244: Karachi | D3244: Original | E3244: North Karachi, Karachi | F3244: Suzuki bolan 2002 outer shower inner original all documents clear mazeed malomat k lia rabta kra 0/3/1/4/2/0/7/7/6/4/5 | G3244: Local | H3244: Manual | I3244: Used
A3245: 1080272866 | B3245: Petrol | C3245: Sindh | D3245: Original | E3245: Bismillah City, Hyderabad | F3245: Selling Mira GSA Model 2015 Registered 2018 Own Power full Engine. . . . Fully Genien Inside and Outside Just Bonnet Touchup ha. . . . No Accident Granted. . . . Document Clear Tax paid December 2023 Demand Rs. 2,515,000/- | G3245: Imported | H3245: Automatic | I3245: Used
A3246: 1080273049 | B3246: Petrol | C3246: Karachi | D3246: Original | E3246: Gulzar-E-Hijri, Karachi | F3246: Good condition all documents CPLC career Inside original outside shower 03,18,27,66,78,3 | G3246: Local | H3246: Manual | I3246: Used
... A3552: 1080347285 | B3552: Petrol | C3552: Karachi | D3552: Original | E3552: Gulshan-e-Iqbal, Karachi | F3552: hijet model 2014 register 2018 first owner documents clear own engine one piece touchup price is almost final time pass walay dor rahain | G3552: Imported | H3552: Automatic | I3552: Used
A3553: 1080347299 | B3553: Petrol | C3553: Karachi | D3553: Original | E3553: Model Town A, Bahawalpur | F3553: #NAME? | G3553: Local | H3553: Manual | I3553: Used
A3554: 1080347316 | B3554: Petrol | C3554: Karachi | D3554: Original | E3554: Gulistan-e-Jauhar Block 3, Karachi | F3554: Suzuki Cultus available for urgent sale need cash engine change mention on papers half self start no work required alloy rims installed air condition in working neat and clean clear interior and exterior documents best for family used price is slightly negoitable urgent need cash | G3554: Local | H3554: Manual | I3554: Used
A3555: 1080347380 | B3555: Petrol | C3555: Lahore | D3555: Original | E3555: Lahore Motorway City - Block R, Lahore | F3555: Selling my own car total genuine rest left door dry dent. Original documents available. Token tax up-to-date. Tyres condition A1 No work required just purchased and drive. Non accidental. Need to sell a car urgently. | G3555: Local | H3555: Manual | I3555: Used
A3556: 1080347565 | B3556: Petrol | C3556: Lahore | D3556: Original | E3556: Green Town, Lahore | F3556: Selling my _ :Daihatsu Mira 2018 Model Demand _ 1,950,000 2 Door LOCATION. . . . . Lahore Bahria Town sector C office * FUNCTIONS . . . . . . *Ac Working *All documents clear *Almost genuine * Registered ,Lahore *Smooth drive *No mechanical work *Original Condition Fog lights lamination sheets Android LCD Back Camera Honda city big seats led head lights * | G3556: Imported | H3556: Automatic | I3556: Used
A3557: 1080347574 | B3557: Petrol | C3557: Lahore | D3557: Original | E3557: Abdul Hakim, Punjab | F3557: City 1.5 Aspire Manual 2016 Model Urban Titanium Color | G3557: Local | H3557: Manual | I3557: Used
A3558: 1080347816 | B3558: Petrol | C3558: Islamabad | D3558: Original | E3558: 7th Avenue, Islamabad | F3558: Honda city Aspire 1.3 manual Islamabad number smart card. . . new tyre installed black colour show Room condition. . . . . smooth petrol average 16 km 2 piece touching. . . . . . zero three one three five four six one seven five eight | G3558: Local | H3558: Manual | I3558: Used
A3559: 1080348107 | B3559: Petrol | C3559: Karachi | D3559: Original | E3559: Wapda Colony, Lahore | F3559: feel like a new car urgent sale | G3559: Local | H3559: Automatic | I3559: Used
A3560: 1080348188 | B3560: Petrol | C3560: Faisalabad | D3560: Original | E3560: Faisalabad, Punjab | F3560: i buy property that's reason | G3560: Local | H3560: Automatic | I3560: Used
A3561: 1080348582 | B3561: Petrol | C3561: Lahore | D3561: Original | E3561: DHA Defence, Lahore | F3561: *Toyota Yaris GLI CVT *Demand : 43.75 lacs *Location : DHA City, Lahore Punjab FUNCTIONS ________ â€¢All documents available â€¢First Owner â€¢100% original â€¢Totally driven on petrol â€¢19053 Kimâ€™s Driven â€¢All taxes paid â€¢Brand new tires installed â€¢Complete original file is availble â€¢Authorized dealership maintained â€¢Price negotiable on spot â€¢ Only serious buyers to contact please More information contact on this Number /whatsapp 1:(0321/478/67/87) | G3561: Local | H3561: Automatic | I3561: Used
A3562: 1080348798 | B3562: Petrol | C3562: Sialkot | D3562: Original | E3562: Saddar, Rawalpindi | F3562: emmaculate condition 10/10 engine is in very condition | G3562: Imported | H3562: Automatic | I3562: Used
A3563: 1080348799 | B3563: Petrol | C3563: Karachi | D3563: Original | E3563: Canal Road, Jhang | F3563: coure model 2007/08 ac in chill working position with dude compressor chat ,digi jenuine, outer shower, inner jenuine dashboard original and clean , non accident CNG kit installed On LPG good avg. 25 se 30 avg on Gas kit just buy and Run family car. | G3563: Local | H3563: Manual | I3563: Used
A3564: 1080348857 | B3564: Petrol | C3564: Karachi | D3564: Original | E3564: Aisha Manzil, Karachi | F3564: original condition over all ok new tayre transfer must | G3564: Imported | H3564: Automatic | I3564: Used
A3565: 1080348887 | B3565: Petrol | C3565: Karachi | D3565: Original | E3565: Defence View Society, Karachi | F3565: Daihatsu Coure CX Model 2004 Chilled AC Shinny Black Metallic Manual Transmission Power Windows Installed Water Dropping Engine No Work in Suspension Inside Full Original Outside Slight Spray for Fresh Look Guarantted No Accident Petrol Only New Seat Covers Tubeless Tyres Great Fuel Average Cplc Clear Complete Original Documents | G3565: Local | H3565: Manual | I3565: Used
... A4494: 1080522842 | B4494: Petrol | C4494: Karachi | D4494: Original | E4494: Gulshan-e-Iqbal, Karachi | F4494: Daihatsu Coure 2007 all documents clear 1.5 year tax not paid converted auto outer shower inside orignal 0/3/3/4/6/6/6/2/2/6/1 | G4494: Local | H4494: Automatic | I4494: Used
A4495: 1080523005 | B4495: Petrol | C4495: Lahore | D4495: Original | E4495: Bahria Enclave 2, Islamabad | F4495: #NAME? | G4495: Local | H4495: Manual | I4495: Used
A4496: 1080523025 | B4496: Petrol | C4496: Lahore | D4496: Original | E4496: DHA Phase 3, Lahore | F4496: Daihatsu terios kit model 2009 import 2013 register 2013 Lahore number orginal book and original file original condition first hand Apna name See in DHA phase 3 | G4496: Local | H4496: Automatic | I4496: Used
A4497: 1080523371 | B4497: Petrol | C4497: Lahore | D4497: Original | E4497: Niazi Chowk, Khanewal | F4497: Honda citi 2019 white colour 1.3 manual token paid | G4497: Imported | H4497: Manual | I4497: Used
A4498: 1080523467 | B4498: Petrol | C4498: Punjab | D4498: Original | E4498: DHA Phase 5, Lahore | F4498: Honda City Aspire 1.5 Prosmatec Total Original 1st owner Brand new tyres Installed Engine,Suspension,Interior Etc Everything 100% | G4498: Local | H4498: Automatic | I4498: Used
A4499: 1080523630 | B4499: Petrol | C4499: Islamabad | D4499: Original | E4499: I-8, Islamabad | F4499: Honda city 2019 prosmatic no touching all documents clear 0300*788*39*61 | G4499: Local | H4499: Automatic | I4499: Used
A4500: 1080523692 | B4500: Petrol | C4500: Islamabad | D4500: Original | E4500: H-13, Islamabad | F4500: Suzuki baleno JXR Islamabad number Smart Card 2nd Owner token updated Engine suspension (Good) tyre 70% paint Condition 70% genuine AC Working water dropping Engine Not Exchange | G4500: Local | H4500: Manual | I4500: Used
A4501: 1080523745 | B4501: Petrol | C4501: Lahore | D4501: Original | E4501: AIMC Residential Colony, Lahore | F4501: Assalam o alaikum I am selling my Honda city 2016 IVTEC as told above everything genuine and original you can contact me on my phone number | G4501: Local | H4501: Manual | I4501: Used
A4502: 1080523770 | B4502: Petrol | C4502: Lahore | D4502: Original | E4502: DHA Defence, Lahore | F4502: Terios Kid 2009/15 Alloy Rims Leather seats Roof Installed Chill Ac Best for city and long range mini jeep 4x4 660CC Total Genuine Paint | G4502: Imported | H4502: Automatic | I4502: Used
A4503: 1080523772 | B4503: Petrol | C4503: Islamabad | D4503: Original | E4503: Pasrur Road, Sialkot | F4503: Condition: Total Gennine , Model 2017 Islamabad Registerd , Face lift into 2021 . Family Used Car Good Fuel Average! Toxen Tax paid, Recently Engine Oil changed No work Required just buy and drive , Chaska Party stay away no dealer Hazrat only serious buyers contact me, Price are flexible ! | G4503: Local | H4503: Automatic | I4503: Used
A4504: 1080524035 | B4504: Petrol | C4504: Islamabad | D4504: Original | E4504: Khayaban-e-Sir Syed, Rawalpindi | F4504: hundai sentro 2003 isl register no work need just buy and drive | G4504: Imported | H4504: Manual | I4504: Used
A4505: 1080524157 | B4505: Petrol | C4505: Lahore | D4505: Original | E4505: E-8/2, Islamabad | F4505: HONDA CITY IVTEC 2011 MODEL for sale. 1st owner One hand used Used by Govt Officer Mostly driven in Islamabad Genuine condition Only serious buyers contact on number after 4 PM Saturday and Sunday contact timing 9 AM to 10 PM | G4505: Local | H4505: Manual | I4505: Used
A4506: 1080524268 | B4506: Petrol | C4506: Karachi | D4506: Original | E4506: Defence View Society, Karachi | F4506: Daihatsu Coure CX Model 2011 Chilled AC Alloyrims New tubeless Tyres Power Windows Power Steering Retractable Side Glasses Water Dropping Engine Apline Player Trumpet Horn Air Press Tinted Glasses New Seat Covers Smooth Noiseless Suspension Original Condition (some pencil scratchess) Petrol Only 2nd Owner Complete File Cplc Clear No Work in Car Just Buy n Drive | G4506: Local | H4506: Manual | I4506: Used
A4507: 1080524380 | B4507: Petrol | C4507: Lahore | D4507: Original | E4507: Shalimar Colony, Multan | F4507: totally genione brand new tyres with alloyrims minor scratch on some piece neat and clean interior lcd with back camera awsome music system installed home used car orignal milage doctor used car just buy and drive exchange possible | G4507: Local | H4507: Manual | I4507: Used
... A4597: 1080536679 | B4597: Petrol | C4597: Karachi | D4597: Original | E4597: Crystal Cottages, Karachi | F4597: Dihatsu Terrios Kid 660 cc Engine Changed model 2002 rec 2007 automatic just like new condition andriod pannel back camera good engine good suspension tubeless tyres alloyrims no rusted | G4597: Imported | H4597: Automatic | I4597: Used
A4598: 1080536754 | B4598: Petrol | C4598: Karachi | D4598: Original | E4598: Federal B Area, Karachi | F4598: #NAME? | G4598: Local | H4598: Manual | I4598: Used
A4599: 1080536810 | B4599: Petrol | C4599: Lahore | D4599: Original | E4599: Bhimber Road, Gujrat | F4599: good condition home use gari ha | G4599: Local | H4599: Manual | I4599: Used
A4600: 1080537619 | B4600: Petrol | C4600: Faisalabad | D4600: Original | E4600: Ghauri Town, Rawalpindi | F4600: suzuki bolan modl. . 2015 no cng only petrol no main accident family used car | G4600: Local | H4600: Manual | I4600: Used
A4601: 1080537712 | B4601: Petrol | C4601: Karachi | D4601: Original | E4601: Gulshan-e-Iqbal, Karachi | F4601: DAIHATSU CUORE 2006 ENGINE 100% A/C ON NEED ONLY GAS SUSPENSION OK NEW TYRES WITH ALLOYRYMS ALL LIGHTS AND GADGETS ARE WORKING INSIDE 100% ORIGINAL CONDITION NON ACCIDENTAL GUARANTEE OUTSIDE ROOF PILLAR DIGGI GENIUNE COMPLETE DOCUMENTS WITH RETURN FILE LOCATION GULSHAN-e-IQBAL 13/DA PLZZZ CALL AND WHATSAPP FOR THIS NUMBER: 0/3/1/3/2/3/4/5/7/7/6 | G4601: Local | H4601: Manual | I4601: Used
A4602: 1080537810 | B4602: Petrol | C4602: Lahore | D4602: Original | E4602: Kasur Raiwind Road, Kasur | F4602: I want to sale my family used car in very good condition 10/9 only interested person contact | G4602: Local | H4602: Manual | I4602: Used
A4603: 1080537903 | B4603: Petrol | C4603: Islamabad | D4603: Original | E4603: Kahuta, Rawalpindi | F4603: honda city,10/10,1st owner | G4603: Local | H4603: Manual | I4603: Used
A4604: 1080538056 | B4604: Petrol | C4604: Sindh | D4604: Original | E4604: Darya Khan Road, Bhakkar | F4604: Honda City 2006 sindh number. New tyres installed, | G4604: Imported | H4604: Manual | I4604: Used
A4605: 1080538170 | B4605: Petrol | C4605: Karachi | D4605: Original | E4605: Naya Nazimabad, Karachi | F4605: suzuki bolan Hi roof very good condition. koi kam nahi hai. cplc clear hai. . contact only call no messg | G4605: Local | H4605: Manual | I4605: Used
A4606: 1080538255 | B4606: Petrol | C4606: Lahore | D4606: Original | E4606: Ferozpur Road, Kasur | F4606: santro 2003 model f | G4606: Local | H4606: Manual | I4606: Used
A4607: 1080538267 | B4607: Petrol | C4607: Karachi | D4607: Original | E4607: Mansehra, Khyber Pakhtunkhwa | F4607: -Toyota Corolla Xli VVTi 2009 -Converted To Gli -Token Tax Upto Date -Total Genuine Only 2 piece Touchup -Brand New Tyre -Brand New Allow Rim -New Battery -Every Thing Is In Working Condition -Sound System -Ac Heater On -Rear Camera -Original Number Plates Available -Perfect Fuel Average 15 city 16 /17 long -2 Digit Vip number -Neat And Clean -No Work Required Just Buy And Drive Family Used Car -Smart Card File By Hand -Only Serious Buyers Can Contact Price Is Negotiate At The Spot - | G4607: Local | H4607: Manual | I4607: Used
A4608: 1080538500 | B4608: Petrol | C4608: Sindh | D4608: Original | E4608: Sitara Park City, Faisalabad | F4608: Well maintained vehicle AC Fully working at idle guaranteed Engine 100% water dropping Only 9000 km driven after Engine Overhaul (Bills Avaialabe) inside genuine outer showered 100% working Vehicle No work required No rust in vehicle. body in good condition no rust See for yourself and then decide Car speaks for its price | G4608: Local | H4608: Manual | I4608: Used
A4609: 1080538680 | B4609: Petrol | C4609: Punjab | D4609: Original | E4609: Gorakhpur, Rawalpindi | F4609: urgent need for cash | G4609: Local | H4609: Manual | I4609: Used
A4610: 1080538691 | B4610: Petrol | C4610: Karachi | D4610: Original | E4610: Scheme 33 - Sector 51-A, Karachi | F4610: Bus lo aur chalao koi masla nahi hay Tubeless tyre Hain New battery hay purani chori hogai thi abhi Dali hay hafta hua hay Total petrol pay chalatay Hain bus company cng kit lagi hue hay Gari Johar main Dekhi ja sakti hay negotiate karnay say pehlay gari ki condition akar dekhlain phr karain aur agar koi waja na Hoti to kabhi sale na karta . Kuch urgent need hogai hay isliye sale karaha hun | G4610: Imported | H4610: Manual | I4610: Used
... A8977: 1080975378 | B8977: CNG | C8977: Karachi | D8977: Duplicate | E8977: Rawalpindi Road, Kohat | F8977: Enjoy the sooper drive. Non accidental guaranteed. Sindh registered. Model 2003. Sealto Seal genuine. Company fitted CNG. Documents clear. Book duplicate. File original. Just 2nd owner. 0/3/3-96/54/9.5. 7. Location Kohat. | G8977: Imported | H8977: Manual | I8977: Used

Sheet Tasks
A1: Ad ID | B1: Car_Name | C1: Make | D1: Make Model | E1: Year | F1: KM_driven | G1: Price | H1: Fuel | I1: Registration_city | J1: Assembly | K1: Transmission | L1: Condition | M1: Selection | N1: Len | O1: Model | P1: Miles_per_year
A2: 1019823763 | B2: Toyota Corolla Altis 1.6 cc | C2: Toyota | D2: Toyota Corrolla Altis | E2: 2015 | F2: 130000 | G2: 4000000 | H2: {=VLOOKUP(A2,Cars_dataset_sheet2!A:I,{2,3,7,8,9},FALSE)} -> Petrol | I2: Karachi | J2: Local | K2: Automatic | L2: Used | M2: =IF(AND(OR(H2="Petrol", H2="CNG"), I2<>"Karachi", NOT(OR(C2="Toyota", C2="Honda"))), "SELECTED", "NOT SELECTED") -> NOT SELECTED | N2: =LEN(D2) -> 21 | O2: =RIGHT(D2, LEN(D2) - FIND(" ", D2)) -> Corrolla Altis | P2: =ROUND((2025-E2),3) -> 10 | S2: , E2))_x000D_
A3: 1032353392 | B3: Mitsubishi mini cab urgent sale | C3: Mitsubishi | D3: Mitsubishi Minica | E3: 2012 | F3: 115000 | G3: 1150000 | H3: {=VLOOKUP(A3,Cars_dataset_sheet2!A:I,{2,3,7,8,9},FALSE)} -> Petrol | I3: Lahore | J3: Imported | K3: Automatic | L3: Used | M3: =IF(AND(OR(H3="Petrol", H3="CNG"), I3<>"Karachi", NOT(OR(C3="Toyota", C3="Honda"))), "SELECTED", "NOT SELECTED") -> SELECTED | N3: =LEN(D3) -> 17 | O3: =RIGHT(D3, LEN(D3) - FIND(" ", D3)) -> Minica | P3: =ROUND((2025-E3),3) -> 13
A4: 1035626806 | B4: Suzuki Every 2013 Model 2019 Registered Jet Black Single hand Use A+ C | C4: Suzuki | D4: Suzuki Every | E4: 2013 | F4: 120000 | G4: 1900000 | H4: {=VLOOKUP(A4,Cars_dataset_sheet2!A:I,{2,3,7,8,9},FALSE)} -> Petrol | I4: Lahore | J4: Imported | K4: Automatic | L4: Used | M4: =IF(AND(OR(H4="Petrol", H4="CNG"), I4<>"Karachi", NOT(OR(C4="Toyota", C4="Honda"))), "SELECTED", "NOT SELECTED") -> SELECTED | N4: =LEN(D4) -> 12 | O4: =RIGHT(D4, LEN(D4) - FIND(" ", D4)) -> Every | P4: =ROUND((2025-E4),3) -> 12
A5: 1036683049 | B5: Mehran 2016 VXR original condition | C5: Suzuki | D5: Suzuki Mehran VXR | E5: 2016 | F5: 38500 | G5: 1180000 | H5: {=VLOOKUP(A5,Cars_dataset_sheet2!A:I,{2,3,7,8,9},FALSE)} -> Petrol | I5: Hyderabad | J5: Local | K5: Manual | L5: Used | M5: =IF(AND(OR(H5="Petrol", H5="CNG"), I5<>"Karachi", NOT(OR(C5="Toyota", C5="Honda"))), "SELECTED", "NOT SELECTED") -> SELECTED | N5: =LEN(D5) -> 17 | O5: =RIGHT(D5, LEN(D5) - FIND(" ", D5)) -> Mehran VXR | P5: =ROUND((2025-E5),3) -> 9
A6: 1036970933 | B6: Daihatsu Cuore 2004 | C6: Daihatsu | D6: Daihatsu Cuore | E6: 2004 | F6: 100000 | G6: 700000 | H6: {=VLOOKUP(A6,Cars_dataset_sheet2!A:I,{2,3,7,8,9},FALSE)} -> Petrol | I6: Karachi | J6: Local | K6: Manual | L6: Used | M6: =IF(AND(OR(H6="Petrol", H6="CNG"), I6<>"Karachi", NOT(OR(C6="Toyota", C6="Honda"))), "SELECTED", "NOT SELECTED") -> NOT SELECTED | N6: =LEN(D6) -> 14 | O6: =RIGHT(D6, LEN(D6) - FIND(" ", D6)) -> Cuore | P6: =ROUND((2025-E6),3) -> 21
A7: 1038612589 | B7: Mitsubishi Minica 2 door Japanese Car for sale | C7: Mitsubishi | D7: Mitsubishi Minica | E7: 2007 | F7: 133500 | G7: 1300000 | H7: {=VLOOKUP(A7,Cars_dataset_sheet2!A:I,{2,3,7,8,9},FALSE)} -> Petrol | I7: Lahore | J7: Imported | K7: Manual | L7: Used | M7: =IF(AND(OR(H7="Petrol", H7="CNG"), I7<>"Karachi", NOT(OR(C7="Toyota", C7="Honda"))), "SELECTED", "NOT SELECTED") -> SELECTED | N7: =LEN(D7) -> 17 | O7: =RIGHT(D7, LEN(D7) - FIND(" ", D7)) -> Minica | P7: =ROUND((2025-E7),3) -> 18
A8: 1043285959 | B8: toyota corolla 2005 | C8: Toyota | D8: Toyota Corolla XLI | E8: 2005 | F8: 195000 | G8: 1750000 | H8: {=VLOOKUP(A8,Cars_dataset_sheet2!A:I,{2,3,7,8,9},FALSE)} -> Petrol | I8: Islamabad | J8: Local | K8: Manual | L8: Used | M8: =IF(AND(OR(H8="Petrol", H8="CNG"), I8<>"Karachi", NOT(OR(C8="Toyota", C8="Honda"))), "SELECTED", "NOT SELECTED") -> NOT SELECTED | N8: =LEN(D8) -> 18 | O8: =RIGHT(D8, LEN(D8) - FIND(" ", D8)) -> Corolla XLI | P8: =ROUND((2025-E8),3) -> 20
A9: 1043893641 | B9: chska party call na kra | C9: KIA | D9: KIA Classic | E9: 2005 | F9: 129049 | G9: 550000 | H9: {=VLOOKUP(A9,Cars_dataset_sheet2!A:I,{2,3,7,8,9},FALSE)} -> Petrol | I9: Islamabad | J9: Local | K9: Manual | L9: Used | M9: =IF(AND(OR(H9="Petrol", H9="CNG"), I9<>"Karachi", NOT(OR(C9="Toyota", C9="Honda"))), "SELECTED", "NOT SELECTED") -> SELECTED | N9: =LEN(D9) -> 11 | O9: =RIGHT(D9, LEN(D9) - FIND(" ", D9)) -> Classic | P9: =ROUND((2025-E9),3) -> 20
A10: 1045295959 | B10: Suzuki Wagon R FA Package 2019 Model 2022 Fresh Import 17360 Km driven | C10: Suzuki | D10: Suzuki Wagon R | E10: 2019 | F10: 18360 | G10: 3500000 | H10: {=VLOOKUP(A10,Cars_dataset_sheet2!A:I,{2,3,7,8,9},FALSE)} -> Petrol | I10: Unregistered | J10: Imported | K10: Automatic | L10: Used | M10: =IF(AND(OR(H10="Petrol", H10="CNG"), I10<>"Karachi", NOT(OR(C10="Toyota", C10="Honda"))), "SELECTED", "NOT SELECTED") -> SELECTED | N10: =LEN(D10) -> 14 | O10: =RIGHT(D10, LEN(D10) - FIND(" ", D10)) -> Wagon R | P10: =ROUND((2025-E10),3) -> 6
A11: 1045445134 | B11: Carry Daaba Minicap Mitsubishi | C11: Mitsubishi | D11: Mitsubishi Minica | E11: 2017 | F11: 170000 | G11: 1500000 | H11: {=VLOOKUP(A11,Cars_dataset_sheet2!A:I,{2,3,7,8,9},FALSE)} -> Petrol | I11: Lahore | J11: Imported | K11: Automatic | L11: Used | M11: =IF(AND(OR(H11="Petrol", H11="CNG"), I11<>"Karachi", NOT(OR(C11="Toyota", C11="Honda"))), "SELECTED", "NOT SELECTED") -> SELECTED | N11: =LEN(D11) -> 17 | O11: =RIGHT(D11, LEN(D11) - FIND(" ", D11)) -> Minica | P11: =ROUND((2025-E11),3) -> 8
A12: 1046475308 | B12: Kia Spectra 2001 1.5 Automatic. Customised price negotiable hai jaldi | C12: KIA | D12: KIA Spectra | E12: 2001 | F12: 50000 | G12: 1200000 | H12: {=VLOOKUP(A12,Cars_dataset_sheet2!A:I,{2,3,7,8,9},FALSE)} -> Petrol | I12: Lahore | J12: Imported | K12: Automatic | L12: Used | M12: =IF(AND(OR(H12="Petrol", H12="CNG"), I12<>"Karachi", NOT(OR(C12="Toyota", C12="Honda"))), "SELECTED", "NOT SELECTED") -> SELECTED | N12: =LEN(D12) -> 11 | O12: =RIGHT(D12, LEN(D12) - FIND(" ", D12)) -> Spectra | P12: =ROUND((2025-E12),3) -> 24
A13: 1046608801 | B13: suzuki every turbo 5gair Exchange posibl with Honda&corola 03195517118 | C13: Suzuki | D13: Suzuki Every | E13: 2016 | F13: 123456 | G13: 1750000 | H13: {=VLOOKUP(A13,Cars_dataset_sheet2!A:I,{2,3,7,8,9},FALSE)} -> Petrol | I13: Lahore | J13: Imported | K13: Automatic | L13: Used | M13: =IF(AND(OR(H13="Petrol", H13="CNG"), I13<>"Karachi", NOT(OR(C13="Toyota", C13="Honda"))), "SELECTED", "NOT SELECTED") -> SELECTED | N13: =LEN(D13) -> 12 | O13: =RIGHT(D13, LEN(D13) - FIND(" ", D13)) -> Every | P13: =ROUND((2025-E13),3) -> 9
A14: 1046845167 | B14: Suzuki Bolan | C14: Suzuki | D14: Suzuki Bolan | E14: 2017 | F14: 38000 | G14: 1300000 | H14: {=VLOOKUP(A14,Cars_dataset_sheet2!A:I,{2,3,7,8,9},FALSE)} -> Petrol | I14: Karachi | J14: Local | K14: Manual | L14: Used | M14: =IF(AND(OR(H14="Petrol", H14="CNG"), I14<>"Karachi", NOT(OR(C14="Toyota", C14="Honda"))), "SELECTED", "NOT SELECTED") -> NOT SELECTED | N14: =LEN(D14) -> 12 | O14: =RIGHT(D14, LEN(D14) - FIND(" ", D14)) -> Bolan | P14: =ROUND((2025-E14),3) -> 8
... A498: 1076289664 | B498: Carry Bolin | C498: Suzuki | D498: Suzuki Bolan | E498: 2019 | F498: 12345 | G498: 1350000 | H498: {=VLOOKUP(A498,Cars_dataset_sheet2!A:I,{2,3,7,8,9},FALSE)} -> CNG | I498: Karachi | J498: Local | K498: Manual | L498: Used | M498: =IF(AND(OR(H498="Petrol", H498="CNG"), I498<>"Karachi", NOT(OR(C498="Toyota", C498="Honda"))), "SELECTED", "NOT SELECTED") -> NOT SELECTED | N498: =LEN(D498) -> 12 | O498: =RIGHT(D498, LEN(D498) - FIND(" ", D498)) -> Bolan | P498: =ROUND((2025-E498),3) -> 6
A499: 1076304786 | B499: 3119111071 | C499: Suzuki | D499: Suzuki Bolan | E499: 2010 | F499: 70000 | G499: 850000 | H499: {=VLOOKUP(A499,Cars_dataset_sheet2!A:I,{2,3,7,8,9},FALSE)} -> CNG | I499: Lahore | J499: Imported | K499: Manual | L499: Used | M499: =IF(AND(OR(H499="Petrol", H499="CNG"), I499<>"Karachi", NOT(OR(C499="Toyota", C499="Honda"))), "SELECTED", "NOT SELECTED") -> SELECTED | N499: =LEN(D499) -> 12 | O499: =RIGHT(D499, LEN(D499) - FIND(" ", D499)) -> Bolan | P499: =ROUND((2025-E499),3) -> 15
A500: 1076307705 | B500: Dihatshu Mira 2012/15 New Condition Exchange with Alto Vxr | C500: Daihatsu | D500: Daihatsu Mira | E500: 2015 | F500: 99000 | G500: 2300000 | H500: {=VLOOKUP(A500,Cars_dataset_sheet2!A:I,{2,3,7,8,9},FALSE)} -> Petrol | I500: Lahore | J500: Imported | K500: Automatic | L500: Used | M500: =IF(AND(OR(H500="Petrol", H500="CNG"), I500<>"Karachi", NOT(OR(C500="Toyota", C500="Honda"))), "SELECTED", "NOT SELECTED") -> SELECTED | N500: =LEN(D500) -> 13 | O500: =RIGHT(D500, LEN(D500) - FIND(" ", D500)) -> Mira | P500: =ROUND((2025-E500),3) -> 10
A501: 1076311882 | B501: Mehran VXR 2008 | C501: Suzuki | D501: Suzuki Mehran VXR | E501: 2008 | F501: 50000 | G501: 750000 | H501: {=VLOOKUP(A501,Cars_dataset_sheet2!A:I,{2,3,7,8,9},FALSE)} -> Petrol | I501: Multan | J501: Local | K501: Manual | L501: Used | M501: =IF(AND(OR(H501="Petrol", H501="CNG"), I501<>"Karachi", NOT(OR(C501="Toyota", C501="Honda"))), "SELECTED", "NOT SELECTED") -> SELECTED | N501: =LEN(D501) -> 17 | O501: =RIGHT(D501, LEN(D501) - FIND(" ", D501)) -> Mehran VXR | P501: =ROUND((2025-E501),3) -> 17
A502: 1076312655 | B502: KIA PICANTO 1.0 AT | C502: KIA | D502: KIA Picanto | E502: 2021 | F502: 18500 | G502: 3150000 | H502: {=VLOOKUP(A502,Cars_dataset_sheet2!A:I,{2,3,7,8,9},FALSE)} -> Petrol | I502: Karachi | J502: Local | K502: Automatic | L502: Used | M502: =IF(AND(OR(H502="Petrol", H502="CNG"), I502<>"Karachi", NOT(OR(C502="Toyota", C502="Honda"))), "SELECTED", "NOT SELECTED") -> NOT SELECTED | N502: =LEN(D502) -> 11 | O502: =RIGHT(D502, LEN(D502) - FIND(" ", D502)) -> Picanto | P502: =ROUND((2025-E502),3) -> 4
A503: 1076320957 | B503: City 2009 -Prosmatic | C503: Honda | D503: Honda City IVTEC | E503: 2009 | F503: 146000 | G503: 2200000 | H503: {=VLOOKUP(A503,Cars_dataset_sheet2!A:I,{2,3,7,8,9},FALSE)} -> Petrol | I503: Sialkot | J503: Local | K503: Automatic | L503: Used | M503: =IF(AND(OR(H503="Petrol", H503="CNG"), I503<>"Karachi", NOT(OR(C503="Toyota", C503="Honda"))), "SELECTED", "NOT SELECTED") -> NOT SELECTED | N503: =LEN(D503) -> 16 | O503: =RIGHT(D503, LEN(D503) - FIND(" ", D503)) -> City IVTEC | P503: =ROUND((2025-E503),3) -> 16
A504: 1076322359 | B504: Santro Club 2004 Urgent Sale | C504: Hyundai | D504: Hyundai Santro | E504: 2004 | F504: 99000 | G504: 650000 | H504: {=VLOOKUP(A504,Cars_dataset_sheet2!A:I,{2,3,7,8,9},FALSE)} -> Petrol | I504: Karachi | J504: Imported | K504: Manual | L504: Used | M504: =IF(AND(OR(H504="Petrol", H504="CNG"), I504<>"Karachi", NOT(OR(C504="Toyota", C504="Honda"))), "SELECTED", "NOT SELECTED") -> NOT SELECTED | N504: =LEN(D504) -> 14 | O504: =RIGHT(D504, LEN(D504) - FIND(" ", D504)) -> Santro | P504: =ROUND((2025-E504),3) -> 21
A505: 1076323992 | B505: Mira Package XSA3 Like a Brand New Car | C505: Daihatsu | D505: Daihatsu Mira | E505: 2019 | F505: 115000 | G505: 3550000 | H505: {=VLOOKUP(A505,Cars_dataset_sheet2!A:I,{2,3,7,8,9},FALSE)} -> Petrol | I505: Karachi | J505: Imported | K505: Automatic | L505: Used | M505: =IF(AND(OR(H505="Petrol", H505="CNG"), I505<>"Karachi", NOT(OR(C505="Toyota", C505="Honda"))), "SELECTED", "NOT SELECTED") -> NOT SELECTED | N505: =LEN(D505) -> 13 | O505: =RIGHT(D505, LEN(D505) - FIND(" ", D505)) -> Mira | P505: =ROUND((2025-E505),3) -> 6
A506: 1076340262 | B506: Carolla Altis 1.6 | C506: Toyota | D506: Toyota Corrolla Altis | E506: 2017 | F506: 90000 | G506: 3900000 | H506: {=VLOOKUP(A506,Cars_dataset_sheet2!A:I,{2,3,7,8,9},FALSE)} -> Petrol | I506: Karachi | J506: Local | K506: Automatic | L506: Used | M506: =IF(AND(OR(H506="Petrol", H506="CNG"), I506<>"Karachi", NOT(OR(C506="Toyota", C506="Honda"))), "SELECTED", "NOT SELECTED") -> NOT SELECTED | N506: =LEN(D506) -> 21 | O506: =RIGHT(D506, LEN(D506) - FIND(" ", D506)) -> Corrolla Altis | P506: =ROUND((2025-E506),3) -> 8
A507: 1076347671 | B507: KIA SPECTRA IN V GOOD CONDITION. (O3OO55O6699) | C507: KIA | D507: KIA Spectra | E507: 2002 | F507: 1234 | G507: 520000 | H507: {=VLOOKUP(A507,Cars_dataset_sheet2!A:I,{2,3,7,8,9},FALSE)} -> Petrol | I507: Sindh | J507: Imported | K507: Manual | L507: Used | M507: =IF(AND(OR(H507="Petrol", H507="CNG"), I507<>"Karachi", NOT(OR(C507="Toyota", C507="Honda"))), "SELECTED", "NOT SELECTED") -> SELECTED | N507: =LEN(D507) -> 11 | O507: =RIGHT(D507, LEN(D507) - FIND(" ", D507)) -> Spectra | P507: =ROUND((2025-E507),3) -> 23
A508: 1076356020 | B508: every 07/12 for sale or Xchang Toyota car | C508: Suzuki | D508: Suzuki Every | E508: 2012 | F508: 200000 | G508: 1260000 | H508: {=VLOOKUP(A508,Cars_dataset_sheet2!A:I,{2,3,7,8,9},FALSE)} -> Petrol | I508: Lahore | J508: Imported | K508: Automatic | L508: Used | M508: =IF(AND(OR(H508="Petrol", H508="CNG"), I508<>"Karachi", NOT(OR(C508="Toyota", C508="Honda"))), "SELECTED", "NOT SELECTED") -> SELECTED | N508: =LEN(D508) -> 12 | O508: =RIGHT(D508, LEN(D508) - FIND(" ", D508)) -> Every | P508: =ROUND((2025-E508),3) -> 13
A509: 1076380433 | B509: suzuki Alto vxr | C509: Suzuki | D509: Suzuki Alto | E509: 2012 | F509: 143000 | G509: 1020000 | H509: {=VLOOKUP(A509,Cars_dataset_sheet2!A:I,{2,3,7,8,9},FALSE)} -> Petrol | I509: Karachi | J509: Local | K509: Manual | L509: Used | M509: =IF(AND(OR(H509="Petrol", H509="CNG"), I509<>"Karachi", NOT(OR(C509="Toyota", C509="Honda"))), "SELECTED", "NOT SELECTED") -> NOT SELECTED | N509: =LEN(D509) -> 11 | O509: =RIGHT(D509, LEN(D509) - FIND(" ", D509)) -> Alto | P509: =ROUND((2025-E509),3) -> 13
A510: 1076380992 | B510: Altis 1.6 automatic 2020/2021 for sale | C510: Toyota | D510: Toyota Corrolla Altis | E510: 2020 | F510: 58000 | G510: 4400000 | H510: {=VLOOKUP(A510,Cars_dataset_sheet2!A:I,{2,3,7,8,9},FALSE)} -> Petrol | I510: Karachi | J510: Local | K510: Automatic | L510: Used | M510: =IF(AND(OR(H510="Petrol", H510="CNG"), I510<>"Karachi", NOT(OR(C510="Toyota", C510="Honda"))), "SELECTED", "NOT SELECTED") -> NOT SELECTED | N510: =LEN(D510) -> 21 | O510: =RIGHT(D510, LEN(D510) - FIND(" ", D510)) -> Corrolla Altis | P510: =ROUND((2025-E510),3) -> 5
A511: 1076385717 | B511: Hyndai santro club 2003 | C511: Hyundai | D511: Hyundai Santro | E511: 2003 | F511: 5555 | G511: 780000 | H511: {=VLOOKUP(A511,Cars_dataset_sheet2!A:I,{2,3,7,8,9},FALSE)} -> Petrol | I511: Lahore | J511: Imported | K511: Manual | L511: Used | M511: =IF(AND(OR(H511="Petrol", H511="CNG"), I511<>"Karachi", NOT(OR(C511="Toyota", C511="Honda"))), "SELECTED", "NOT SELECTED") -> SELECTED | N511: =LEN(D511) -> 14 | O511: =RIGHT(D511, LEN(D511) - FIND(" ", D511)) -> Santro | P511: =ROUND((2025-E511),3) -> 22
... A730: 1077566598 | B730: 1.5 Honda City Aspire in Brand New Condition | C730: Honda | D730: Honda City Aspire | E730: 2017 | F730: 51000 | G730: 3250000 | H730: {=VLOOKUP(A730,Cars_dataset_sheet2!A:I,{2,3,7,8,9},FALSE)} -> Petrol | I730: Karachi | J730: Local | K730: Manual | L730: Used | M730: =IF(AND(OR(H730="Petrol", H730="CNG"), I730<>"Karachi", NOT(OR(C730="Toyota", C730="Honda"))), "SELECTED", "NOT SELECTED") -> NOT SELECTED | N730: =LEN(D730) -> 17 | O730: =RIGHT(D730, LEN(D730) - FIND(" ", D730)) -> City Aspire | P730: =ROUND((2025-E730),3) -> 8
A731: 1077567793 | B731: 3002195137 | C731: Suzuki | D731: Suzuki Bolan | E731: 2017 | F731: 62000 | G731: 1150000 | H731: {=VLOOKUP(A731,Cars_dataset_sheet2!A:I,{2,3,7,8,9},FALSE)} -> Petrol | I731: Karachi | J731: Imported | K731: Manual | L731: Used | M731: =IF(AND(OR(H731="Petrol", H731="CNG"), I731<>"Karachi", NOT(OR(C731="Toyota", C731="Honda"))), "SELECTED", "NOT SELECTED") -> NOT SELECTED | N731: =LEN(D731) -> 12 | O731: =RIGHT(D731, LEN(D731) - FIND(" ", D731)) -> Bolan | P731: =ROUND((2025-E731),3) -> 8
A732: 1077572197 | B732: Mitsubishi Lancer 2005 model in good condition | C732: Mitsubishi | D732: Mitsubishi Lancer | E732: 2005 | F732: 70000 | G732: 1370000 | H732: {=VLOOKUP(A732,Cars_dataset_sheet2!A:I,{2,3,7,8,9},FALSE)} -> Petrol | I732: Lahore | J732: Imported | K732: Manual | L732: Used | M732: =IF(AND(OR(H732="Petrol", H732="CNG"), I732<>"Karachi", NOT(OR(C732="Toyota", C732="Honda"))), "SELECTED", "NOT SELECTED") -> SELECTED | N732: =LEN(D732) -> 17 | O732: =RIGHT(D732, LEN(D732) - FIND(" ", D732)) -> Lancer | P732: =ROUND((2025-E732),3) -> 20
A733: 1077576628 | B733: dihatsu move urgent sale | C733: Daihatsu | D733: Daihatsu Move | E733: 2021 | F733: 100000 | G733: 2900000 | H733: {=VLOOKUP(A733,Cars_dataset_sheet2!A:I,{2,3,7,8,9},FALSE)} -> Petrol | I733: Punjab | J733: Imported | K733: Automatic | L733: Used | M733: =IF(AND(OR(H733="Petrol", H733="CNG"), I733<>"Karachi", NOT(OR(C733="Toyota", C733="Honda"))), "SELECTED", "NOT SELECTED") -> SELECTED | N733: =LEN(D733) -> 13 | O733: =RIGHT(D733, LEN(D733) - FIND(" ", D733)) -> Move | P733: =ROUND((2025-E733),3) -> 4
A734: 1077577910 | B734: honda city 2010 | C734: Honda | D734: Honda City IVTEC | E734: 2010 | F734: 145000 | G734: 2500000 | H734: {=VLOOKUP(A734,Cars_dataset_sheet2!A:I,{2,3,7,8,9},FALSE)} -> Petrol | I734: Lahore | J734: Local | K734: Manual | L734: Used | M734: =IF(AND(OR(H734="Petrol", H734="CNG"), I734<>"Karachi", NOT(OR(C734="Toyota", C734="Honda"))), "SELECTED", "NOT SELECTED") -> NOT SELECTED | N734: =LEN(D734) -> 16 | O734: =RIGHT(D734, LEN(D734) - FIND(" ", D734)) -> City IVTEC | P734: =ROUND((2025-E734),3) -> 15
A735: 1077578497 | B735: Honda civic reborn | C735: Honda | D735: Honda Civic Prosmetic | E735: 2009 | F735: 97000 | G735: 1800000 | H735: {=VLOOKUP(A735,Cars_dataset_sheet2!A:I,{2,3,7,8,9},FALSE)} -> Petrol | I735: Sindh | J735: Local | K735: Automatic | L735: Used | M735: =IF(AND(OR(H735="Petrol", H735="CNG"), I735<>"Karachi", NOT(OR(C735="Toyota", C735="Honda"))), "SELECTED", "NOT SELECTED") -> NOT SELECTED | N735: =LEN(D735) -> 21 | O735: =RIGHT(D735, LEN(D735) - FIND(" ", D735)) -> Civic Prosmetic | P735: =ROUND((2025-E735),3) -> 16
A736: 1077580298 | B736: Cuore 2012 | C736: Daihatsu | D736: Daihatsu Cuore | E736: 2012 | F736: 120000 | G736: 865000 | H736: {=VLOOKUP(A736,Cars_dataset_sheet2!A:I,{2,3,7,8,9},FALSE)} -> Petrol | I736: Sindh | J736: Imported | K736: Manual | L736: Used | M736: =IF(AND(OR(H736="Petrol", H736="CNG"), I736<>"Karachi", NOT(OR(C736="Toyota", C736="Honda"))), "SELECTED", "NOT SELECTED") -> SELECTED | N736: =LEN(D736) -> 14 | O736: =RIGHT(D736, LEN(D736) - FIND(" ", D736)) -> Cuore | P736: =ROUND((2025-E736),3) -> 13
A737: 1077583006 | B737: honda city 1.3 Mt | C737: Honda | D737: Honda City IVTEC | E737: 2019 | F737: 58000 | G737: 3500000 | H737: {=VLOOKUP(A737,Cars_dataset_sheet2!A:I,{2,3,7,8,9},FALSE)} -> Petrol | I737: Lahore | J737: Local | K737: Manual | L737: Used | M737: =IF(AND(OR(H737="Petrol", H737="CNG"), I737<>"Karachi", NOT(OR(C737="Toyota", C737="Honda"))), "SELECTED", "NOT SELECTED") -> NOT SELECTED | N737: =LEN(D737) -> 16 | O737: =RIGHT(D737, LEN(D737) - FIND(" ", D737)) -> City IVTEC | P737: =ROUND((2025-E737),3) -> 6
A738: 1077583460 | B738: Ek Wagon 2008/2013 [660cc] | C738: Mitsubishi | D738: Mitsubishi Ek Wagon | E738: 2008 | F738: 140000 | G738: 1700000 | H738: {=VLOOKUP(A738,Cars_dataset_sheet2!A:I,{2,3,7,8,9},FALSE)} -> Petrol | I738: Punjab | J738: Imported | K738: Manual | L738: Used | M738: =IF(AND(OR(H738="Petrol", H738="CNG"), I738<>"Karachi", NOT(OR(C738="Toyota", C738="Honda"))), "SELECTED", "NOT SELECTED") -> SELECTED | N738: =LEN(D738) -> 19 | O738: =RIGHT(D738, LEN(D738) - FIND(" ", D738)) -> Ek Wagon | P738: =ROUND((2025-E738),3) -> 17
A739: 1077592008 | B739: Mercedes C 200 Kompressor | C739: Mercedes | D739: Mercedes C Class | E739: 2003 | F739: 200000 | G739: 2300000 | H739: {=VLOOKUP(A739,Cars_dataset_sheet2!A:I,{2,3,7,8,9},FALSE)} -> Petrol | I739: Sindh | J739: Imported | K739: Automatic | L739: Used | M739: =IF(AND(OR(H739="Petrol", H739="CNG"), I739<>"Karachi", NOT(OR(C739="Toyota", C739="Honda"))), "SELECTED", "NOT SELECTED") -> SELECTED | N739: =LEN(D739) -> 16 | O739: =RIGHT(D739, LEN(D739) - FIND(" ", D739)) -> C Class | P739: =ROUND((2025-E739),3) -> 22
A740: 1077609801 | B740: i am selling my lancer glx 1.5 automatic | C740: Mitsubishi | D740: Mitsubishi Lancer | E740: 2006 | F740: 65000 | G740: 1550000 | H740: {=VLOOKUP(A740,Cars_dataset_sheet2!A:I,{2,3,7,8,9},FALSE)} -> Petrol | I740: Karachi | J740: Imported | K740: Automatic | L740: Used | M740: =IF(AND(OR(H740="Petrol", H740="CNG"), I740<>"Karachi", NOT(OR(C740="Toyota", C740="Honda"))), "SELECTED", "NOT SELECTED") -> NOT SELECTED | N740: =LEN(D740) -> 17 | O740: =RIGHT(D740, LEN(D740) - FIND(" ", D740)) -> Lancer | P740: =ROUND((2025-E740),3) -> 19
A741: 1077612923 | B741: Mira model 2014 registration 2017 | C741: Daihatsu | D741: Daihatsu Mira | E741: 2014 | F741: 119000 | G741: 2460000 | H741: {=VLOOKUP(A741,Cars_dataset_sheet2!A:I,{2,3,7,8,9},FALSE)} -> Petrol | I741: Karachi | J741: Imported | K741: Automatic | L741: Used | M741: =IF(AND(OR(H741="Petrol", H741="CNG"), I741<>"Karachi", NOT(OR(C741="Toyota", C741="Honda"))), "SELECTED", "NOT SELECTED") -> NOT SELECTED | N741: =LEN(D741) -> 13 | O741: =RIGHT(D741, LEN(D741) - FIND(" ", D741)) -> Mira | P741: =ROUND((2025-E741),3) -> 11
A742: 1077614644 | B742: Honda City IDSI Vario | C742: Honda | D742: Honda City Vario | E742: 2007 | F742: 79000 | G742: 1680000 | H742: {=VLOOKUP(A742,Cars_dataset_sheet2!A:I,{2,3,7,8,9},FALSE)} -> Petrol | I742: Karachi | J742: Local | K742: Automatic | L742: Used | M742: =IF(AND(OR(H742="Petrol", H742="CNG"), I742<>"Karachi", NOT(OR(C742="Toyota", C742="Honda"))), "SELECTED", "NOT SELECTED") -> NOT SELECTED | N742: =LEN(D742) -> 16 | O742: =RIGHT(D742, LEN(D742) - FIND(" ", D742)) -> City Vario | P742: =ROUND((2025-E742),3) -> 18
A743: 1077617252 | B743: sentro Hyundai | C743: Hyundai | D743: Hyundai Santro | E743: 2006 | F743: 17000 | G743: 849999 | H743: {=VLOOKUP(A743,Cars_dataset_sheet2!A:I,{2,3,7,8,9},FALSE)} -> Petrol | I743: Lahore | J743: Local | K743: Manual | L743: Used | M743: =IF(AND(OR(H743="Petrol", H743="CNG"), I743<>"Karachi", NOT(OR(C743="Toyota", C743="Honda"))), "SELECTED", "NOT SELECTED") -> SELECTED | N743: =LEN(D743) -> 14 | O743: =RIGHT(D743, LEN(D743) - FIND(" ", D743)) -> Santro | P743: =ROUND((2025-E743),3) -> 19
... A747: 1077637008 | B747: Suzuki every 7/12/15 | C747: Suzuki | D747: Suzuki Every | E747: 2015 | F747: 140000 | G747: 1185000 | H747: {=VLOOKUP(A747,Cars_dataset_sheet2!A:I,{2,3,7,8,9},FALSE)} -> Petrol | I747: Sialkot | J747: Imported | K747: Automatic | L747: Used | M747: =IF(AND(OR(H747="Petrol", H747="CNG"), I747<>"Karachi", NOT(OR(C747="Toyota", C747="Honda"))), "SELECTED", "NOT SELECTED") -> SELECTED | N747: =LEN(D747) -> 12 | O747: =RIGHT(D747, LEN(D747) - FIND(" ", D747)) -> Every | P747: =ROUND((2025-E747),3) -> 10
A748: 1077647354 | B748: 3086863882 | C748: Honda | D748: Honda City Vario | E748: 2006 | F748: 170000 | G748: 1770000 | H748: {=VLOOKUP(A748,Cars_dataset_sheet2!A:I,{2,3,7,8,9},FALSE)} -> Petrol | I748: Lahore | J748: Imported | K748: Automatic | L748: Used | M748: =IF(AND(OR(H748="Petrol", H748="CNG"), I748<>"Karachi", NOT(OR(C748="Toyota", C748="Honda"))), "SELECTED", "NOT SELECTED") -> NOT SELECTED | N748: =LEN(D748) -> 16 | O748: =RIGHT(D748, LEN(D748) - FIND(" ", D748)) -> City Vario | P748: =ROUND((2025-E748),3) -> 19
A749: 1077651584 | B749: Daihatsu tarios 2011 full option | C749: Daihatsu | D749: Daihatsu Terios Kid | E749: 2011 | F749: 250000 | G749: 4000000 | H749: {=VLOOKUP(A749,Cars_dataset_sheet2!A:I,{2,3,7,8,9},FALSE)} -> Petrol | I749: Islamabad | J749: Imported | K749: Automatic | L749: Used | M749: =IF(AND(OR(H749="Petrol", H749="CNG"), I749<>"Karachi", NOT(OR(C749="Toyota", C749="Honda"))), "SELECTED", "NOT SELECTED") -> SELECTED | N749: =LEN(D749) -> 19 | O749: =RIGHT(D749, LEN(D749) - FIND(" ", D749)) -> Terios Kid | P749: =ROUND((2025-E749),3) -> 14
A750: 1077660847 | B750: Wagon R 2018 Full Perfect Never Open 0 Accident | C750: Suzuki | D750: Suzuki Wagon R | E750: 2018 | F750: 93575 | G750: 1925000 | H750: {=VLOOKUP(A750,Cars_dataset_sheet2!A:I,{2,3,7,8,9},FALSE)} -> Petrol | I750: Lahore | J750: Imported | K750: Manual | L750: Used | M750: =IF(AND(OR(H750="Petrol", H750="CNG"), I750<>"Karachi", NOT(OR(C750="Toyota", C750="Honda"))), "SELECTED", "NOT SELECTED") -> SELECTED | N750: =LEN(D750) -> 14 | O750: =RIGHT(D750, LEN(D750) - FIND(" ", D750)) -> Wagon R | P750: =ROUND((2025-E750),3) -> 7
A751: 1077674292 | B751: Honda civic Rebirth | C751: Honda | D751: Honda Civic Oriel | E751: 2013 | F751: 140000 | G751: 3280000 | H751: {=VLOOKUP(A751,Cars_dataset_sheet2!A:I,{2,3,7,8,9},FALSE)} -> Petrol | I751: Islamabad | J751: Local | K751: Manual | L751: Used | M751: =IF(AND(OR(H751="Petrol", H751="CNG"), I751<>"Karachi", NOT(OR(C751="Toyota", C751="Honda"))), "SELECTED", "NOT SELECTED") -> NOT SELECTED | N751: =LEN(D751) -> 17 | O751: =RIGHT(D751, LEN(D751) - FIND(" ", D751)) -> Civic Oriel | P751: =ROUND((2025-E751),3) -> 12
A752: 1077674415 | B752: Mercedes C180 2008 model Islamabad registered | C752: Mercedes | D752: Mercedes C Class | E752: 2008 | F752: 117000 | G752: 4900000 | H752: {=VLOOKUP(A752,Cars_dataset_sheet2!A:I,{2,3,7,8,9},FALSE)} -> Petrol | I752: Islamabad | J752: Imported | K752: Automatic | L752: Used | M752: =IF(AND(OR(H752="Petrol", H752="CNG"), I752<>"Karachi", NOT(OR(C752="Toyota", C752="Honda"))), "SELECTED", "NOT SELECTED") -> SELECTED | N752: =LEN(D752) -> 16 | O752: =RIGHT(D752, LEN(D752) - FIND(" ", D752)) -> C Class | P752: =ROUND((2025-E752),3) -> 17
A753: 1077676902 | B753: Mira 2011-15 | C753: Daihatsu | D753: Daihatsu Mira | E753: 2011 | F753: 100000 | G753: 2050000 | H753: {=VLOOKUP(A753,Cars_dataset_sheet2!A:I,{2,3,7,8,9},FALSE)} -> Petrol | I753: Karachi | J753: Imported | K753: Automatic | L753: Used | M753: =IF(AND(OR(H753="Petrol", H753="CNG"), I753<>"Karachi", NOT(OR(C753="Toyota", C753="Honda"))), "SELECTED", "NOT SELECTED") -> NOT SELECTED | N753: =LEN(D753) -> 13 | O753: =RIGHT(D753, LEN(D753) - FIND(" ", D753)) -> Mira | P753: =ROUND((2025-E753),3) -> 14
A754: 1077679088 | B754: suzuki cultus for sale | C754: Suzuki | D754: Suzuki Cultus VXR | E754: 2001 | F754: 150000 | G754: 570000 | H754: {=VLOOKUP(A754,Cars_dataset_sheet2!A:I,{2,3,7,8,9},FALSE)} -> Petrol | I754: Lahore | J754: Local | K754: Manual | L754: Used | M754: =IF(AND(OR(H754="Petrol", H754="CNG"), I754<>"Karachi", NOT(OR(C754="Toyota", C754="Honda"))), "SELECTED", "NOT SELECTED") -> SELECTED | N754: =LEN(D754) -> 17 | O754: =RIGHT(D754, LEN(D754) - FIND(" ", D754)) -> Cultus VXR | P754: =ROUND((2025-E754),3) -> 24
A755: 1077687947 | B755: Suzuki Every fully loaded For Sale | C755: Suzuki | D755: Suzuki Every | E755: 2016 | F755: 59000 | G755: 2390000 | H755: {=VLOOKUP(A755,Cars_dataset_sheet2!A:I,{2,3,7,8,9},FALSE)} -> Petrol | I755: Punjab | J755: Imported | K755: Automatic | L755: Used | M755: =IF(AND(OR(H755="Petrol", H755="CNG"), I755<>"Karachi", NOT(OR(C755="Toyota", C755="Honda"))), "SELECTED", "NOT SELECTED") -> SELECTED | N755: =LEN(D755) -> 12 | O755: =RIGHT(D755, LEN(D755) - FIND(" ", D755)) -> Every | P755: =ROUND((2025-E755),3) -> 9
A756: 1077690189 | B756: I'm selling my swift car in good condition not a single work required. | C756: Suzuki | D756: Suzuki Swift | E756: 2017 | F756: 79000 | G756: 2400000 | H756: {=VLOOKUP(A756,Cars_dataset_sheet2!A:I,{2,3,7,8,9},FALSE)} -> Petrol | I756: Karachi | J756: Local | K756: Automatic | L756: Used | M756: =IF(AND(OR(H756="Petrol", H756="CNG"), I756<>"Karachi", NOT(OR(C756="Toyota", C756="Honda"))), "SELECTED", "NOT SELECTED") -> NOT SELECTED | N756: =LEN(D756) -> 12 | O756: =RIGHT(D756, LEN(D756) - FIND(" ", D756)) -> Swift | P756: =ROUND((2025-E756),3) -> 8
A757: 1077693334 | B757: Toyota altis grande 2018 | C757: Toyota | D757: Toyota Altis Grande | E757: 2018 | F757: 99850 | G757: 5000000 | H757: {=VLOOKUP(A757,Cars_dataset_sheet2!A:I,{2,3,7,8,9},FALSE)} -> Petrol | I757: Lahore | J757: Local | K757: Automatic | L757: Used | M757: =IF(AND(OR(H757="Petrol", H757="CNG"), I757<>"Karachi", NOT(OR(C757="Toyota", C757="Honda"))), "SELECTED", "NOT SELECTED") -> NOT SELECTED | N757: =LEN(D757) -> 19 | O757: =RIGHT(D757, LEN(D757) - FIND(" ", D757)) -> Altis Grande | P757: =ROUND((2025-E757),3) -> 7
A758: 1077694829 | B758: Toyota pixis | C758: Daihatsu | D758: Daihatsu Mira | E758: 2015 | F758: 89000 | G758: 2230000 | H758: {=VLOOKUP(A758,Cars_dataset_sheet2!A:I,{2,3,7,8,9},FALSE)} -> Petrol | I758: Islamabad | J758: Imported | K758: Automatic | L758: Used | M758: =IF(AND(OR(H758="Petrol", H758="CNG"), I758<>"Karachi", NOT(OR(C758="Toyota", C758="Honda"))), "SELECTED", "NOT SELECTED") -> SELECTED | N758: =LEN(D758) -> 13 | O758: =RIGHT(D758, LEN(D758) - FIND(" ", D758)) -> Mira | P758: =ROUND((2025-E758),3) -> 10
A759: 1077700845 | B759: Honda city Almost Geniun for sale | C759: Honda | D759: Honda City IDSI | E759: 2005 | F759: 200000 | G759: 1550000 | H759: {=VLOOKUP(A759,Cars_dataset_sheet2!A:I,{2,3,7,8,9},FALSE)} -> Petrol | I759: Lahore | J759: Local | K759: Manual | L759: Used | M759: =IF(AND(OR(H759="Petrol", H759="CNG"), I759<>"Karachi", NOT(OR(C759="Toyota", C759="Honda"))), "SELECTED", "NOT SELECTED") -> NOT SELECTED | N759: =LEN(D759) -> 15 | O759: =RIGHT(D759, LEN(D759) - FIND(" ", D759)) -> City IDSI | P759: =ROUND((2025-E759),3) -> 20
A760: 1077708945 | B760: Toyota Passo | C760: Toyota | D760: Toyota Passo | E760: 2013 | F760: 135000 | G760: 2475000 | H760: {=VLOOKUP(A760,Cars_dataset_sheet2!A:I,{2,3,7,8,9},FALSE)} -> Petrol | I760: Karachi | J760: Imported | K760: Automatic | L760: Used | M760: =IF(AND(OR(H760="Petrol", H760="CNG"), I760<>"Karachi", NOT(OR(C760="Toyota", C760="Honda"))), "SELECTED", "NOT SELECTED") -> NOT SELECTED | N760: =LEN(D760) -> 12 | O760: =RIGHT(D760, LEN(D760) - FIND(" ", D760)) -> Passo | P760: =ROUND((2025-E760),3) -> 12
... A1014: 1078384970 | B1014: passo 2013 model reg 2017 | C1014: Toyota | D1014: Toyota Passo | E1014: 2013 | F1014: 96000 | G1014: 2725000 | H1014: {=VLOOKUP(A1014,Cars_dataset_sheet2!A:I,{2,3,7,8,9},FALSE)} -> Petrol | I1014: Islamabad | J1014: Imported | K1014: Automatic | L1014: Used | M1014: =IF(AND(OR(H1014="Petrol", H1014="CNG"), I1014<>"Karachi", NOT(OR(C1014="Toyota", C1014="Honda"))), "SELECTED", "NOT SELECTED") -> NOT SELECTED | N1014: =LEN(D1014) -> 12 | O1014: =RIGHT(D1014, LEN(D1014) - FIND(" ", D1014)) -> Passo | P1014: =ROUND((2025-E1014),3) -> 12
A1015: 1078387916 | B1015: 45575 | C1015: Honda | D1015: Honda City Aspire | E1015: 2013 | F1015: 106500 | G1015: 2700000 | H1015: {=VLOOKUP(A1015,Cars_dataset_sheet2!A:I,{2,3,7,8,9},FALSE)} -> Petrol | I1015: Lahore | J1015: Local | K1015: Automatic | L1015: Used | M1015: =IF(AND(OR(H1015="Petrol", H1015="CNG"), I1015<>"Karachi", NOT(OR(C1015="Toyota", C1015="Honda"))), "SELECTED", "NOT SELECTED") -> NOT SELECTED | N1015: =LEN(D1015) -> 17 | O1015: =RIGHT(D1015, LEN(D1015) - FIND(" ", D1015)) -> City Aspire | P1015: =ROUND((2025-E1015),3) -> 12
A1016: 1078391403 | B1016: Special Suzuki Every Wagon for sale in low price. | C1016: Suzuki | D1016: Suzuki Every | E1016: 2010 | F1016: 200000 | G1016: 2500000 | H1016: {=VLOOKUP(A1016,Cars_dataset_sheet2!A:I,{2,3,7,8,9},FALSE)} -> Petrol | I1016: Islamabad | J1016: Imported | K1016: Automatic | L1016: Used | M1016: =IF(AND(OR(H1016="Petrol", H1016="CNG"), I1016<>"Karachi", NOT(OR(C1016="Toyota", C1016="Honda"))), "SELECTED", "NOT SELECTED") -> SELECTED | N1016: =LEN(D1016) -> 12 | O1016: =RIGHT(D1016, LEN(D1016) - FIND(" ", D1016)) -> Every | P1016: =ROUND((2025-E1016),3) -> 15
A1017: 1078400918 | B1017: Suzuki every Hijet clipper | C1017: Suzuki | D1017: Suzuki Every | E1017: 2016 | F1017: 108888 | G1017: 1365000 | H1017: {=VLOOKUP(A1017,Cars_dataset_sheet2!A:I,{2,3,7,8,9},FALSE)} -> Petrol | I1017: Karachi | J1017: Imported | K1017: Automatic | L1017: Used | M1017: =IF(AND(OR(H1017="Petrol", H1017="CNG"), I1017<>"Karachi", NOT(OR(C1017="Toyota", C1017="Honda"))), "SELECTED", "NOT SELECTED") -> NOT SELECTED | N1017: =LEN(D1017) -> 12 | O1017: =RIGHT(D1017, LEN(D1017) - FIND(" ", D1017)) -> Every | P1017: =ROUND((2025-E1017),3) -> 9
A1018: 1078403773 | B1018: Honda city 2007 silver original condition | C1018: Honda | D1018: Honda City IDSI | E1018: 2007 | F1018: 12345 | G1018: 1575000 | H1018: {=VLOOKUP(A1018,Cars_dataset_sheet2!A:I,{2,3,7,8,9},FALSE)} -> Petrol | I1018: Karachi | J1018: Local | K1018: Manual | L1018: Used | M1018: =IF(AND(OR(H1018="Petrol", H1018="CNG"), I1018<>"Karachi", NOT(OR(C1018="Toyota", C1018="Honda"))), "SELECTED", "NOT SELECTED") -> NOT SELECTED | N1018: =LEN(D1018) -> 15 | O1018: =RIGHT(D1018, LEN(D1018) - FIND(" ", D1018)) -> City IDSI | P1018: =ROUND((2025-E1018),3) -> 18
A1019: 1078407463 | B1019: Alto 2020 VXR | C1019: Suzuki | D1019: Suzuki Alto | E1019: 2020 | F1019: 65000 | G1019: 2290000 | H1019: {=VLOOKUP(A1019,Cars_dataset_sheet2!A:I,{2,3,7,8,9},FALSE)} -> Petrol | I1019: Punjab | J1019: Local | K1019: Automatic | L1019: Used | M1019: =IF(AND(OR(H1019="Petrol", H1019="CNG"), I1019<>"Karachi", NOT(OR(C1019="Toyota", C1019="Honda"))), "SELECTED", "NOT SELECTED") -> SELECTED | N1019: =LEN(D1019) -> 11 | O1019: =RIGHT(D1019, LEN(D1019) - FIND(" ", D1019)) -> Alto | P1019: =ROUND((2025-E1019),3) -> 5
A1020: 1078407721 | B1020: Suzuki Mehran VXR 2017/18 | C1020: Suzuki | D1020: Suzuki Mehran VXR | E1020: 2017 | F1020: 45000 | G1020: 1299000 | H1020: {=VLOOKUP(A1020,Cars_dataset_sheet2!A:I,{2,3,7,8,9},FALSE)} -> Petrol | I1020: Lahore | J1020: Local | K1020: Manual | L1020: Used | M1020: =IF(AND(OR(H1020="Petrol", H1020="CNG"), I1020<>"Karachi", NOT(OR(C1020="Toyota", C1020="Honda"))), "SELECTED", "NOT SELECTED") -> SELECTED | N1020: =LEN(D1020) -> 17 | O1020: =RIGHT(D1020, LEN(D1020) - FIND(" ", D1020)) -> Mehran VXR | P1020: =ROUND((2025-E1020),3) -> 8
A1021: 1078407880 | B1021: Selling my Daihatsu Terios Kid | C1021: Daihatsu | D1021: Daihatsu Terios Kid | E1021: 2008 | F1021: 150000 | G1021: 1680000 | H1021: {=VLOOKUP(A1021,Cars_dataset_sheet2!A:I,{2,3,7,8,9},FALSE)} -> Petrol | I1021: Sindh | J1021: Imported | K1021: Automatic | L1021: Used | M1021: =IF(AND(OR(H1021="Petrol", H1021="CNG"), I1021<>"Karachi", NOT(OR(C1021="Toyota", C1021="Honda"))), "SELECTED", "NOT SELECTED") -> SELECTED | N1021: =LEN(D1021) -> 19 | O1021: =RIGHT(D1021, LEN(D1021) - FIND(" ", D1021)) -> Terios Kid | P1021: =ROUND((2025-E1021),3) -> 17
A1022: 1078408201 | B1022: WAGONR VXL 2021 | C1022: Suzuki | D1022: Suzuki Wagon R | E1022: 2021 | F1022: 45000 | G1022: 2490000 | H1022: {=VLOOKUP(A1022,Cars_dataset_sheet2!A:I,{2,3,7,8,9},FALSE)} -> Petrol | I1022: Punjab | J1022: Local | K1022: Manual | L1022: Used | M1022: =IF(AND(OR(H1022="Petrol", H1022="CNG"), I1022<>"Karachi", NOT(OR(C1022="Toyota", C1022="Honda"))), "SELECTED", "NOT SELECTED") -> SELECTED | N1022: =LEN(D1022) -> 14 | O1022: =RIGHT(D1022, LEN(D1022) - FIND(" ", D1022)) -> Wagon R | P1022: =ROUND((2025-E1022),3) -> 4
A1023: 1078409586 | B1023: cultus 2006 for sale | C1023: Suzuki | D1023: Suzuki Cultus VXR | E1023: 2006 | F1023: 70374 | G1023: 750000 | H1023: {=VLOOKUP(A1023,Cars_dataset_sheet2!A:I,{2,3,7,8,9},FALSE)} -> Petrol | I1023: Lahore | J1023: Local | K1023: Manual | L1023: Used | M1023: =IF(AND(OR(H1023="Petrol", H1023="CNG"), I1023<>"Karachi", NOT(OR(C1023="Toyota", C1023="Honda"))), "SELECTED", "NOT SELECTED") -> SELECTED | N1023: =LEN(D1023) -> 17 | O1023: =RIGHT(D1023, LEN(D1023) - FIND(" ", D1023)) -> Cultus VXR | P1023: =ROUND((2025-E1023),3) -> 19
A1024: 1078412721 | B1024: Toyota Corolla XLI 2010/11 urgently sale | C1024: Toyota | D1024: Toyota Corolla XLI | E1024: 2011 | F1024: 110325 | G1024: 1890000 | H1024: {=VLOOKUP(A1024,Cars_dataset_sheet2!A:I,{2,3,7,8,9},FALSE)} -> Petrol | I1024: Sindh | J1024: Imported | K1024: Manual | L1024: Used | M1024: =IF(AND(OR(H1024="Petrol", H1024="CNG"), I1024<>"Karachi", NOT(OR(C1024="Toyota", C1024="Honda"))), "SELECTED", "NOT SELECTED") -> NOT SELECTED | N1024: =LEN(D1024) -> 18 | O1024: =RIGHT(D1024, LEN(D1024) - FIND(" ", D1024)) -> Corolla XLI | P1024: =ROUND((2025-E1024),3) -> 14
A1025: 1078413809 | B1025: Baleno silver. 2005 | C1025: Suzuki | D1025: Suzuki Baleno | E1025: 2005 | F1025: 290000 | G1025: 910000 | H1025: {=VLOOKUP(A1025,Cars_dataset_sheet2!A:I,{2,3,7,8,9},FALSE)} -> Petrol | I1025: Sargodha | J1025: Imported | K1025: Manual | L1025: Used | M1025: =IF(AND(OR(H1025="Petrol", H1025="CNG"), I1025<>"Karachi", NOT(OR(C1025="Toyota", C1025="Honda"))), "SELECTED", "NOT SELECTED") -> SELECTED | N1025: =LEN(D1025) -> 13 | O1025: =RIGHT(D1025, LEN(D1025) - FIND(" ", D1025)) -> Baleno | P1025: =ROUND((2025-E1025),3) -> 20
A1026: 1078418976 | B1026: Daihatsu Hijet 2013 | C1026: Daihatsu | D1026: Daihatsu Hijet | E1026: 2013 | F1026: 50000 | G1026: 1450000 | H1026: {=VLOOKUP(A1026,Cars_dataset_sheet2!A:I,{2,3,7,8,9},FALSE)} -> Petrol | I1026: Karachi | J1026: Imported | K1026: Automatic | L1026: Used | M1026: =IF(AND(OR(H1026="Petrol", H1026="CNG"), I1026<>"Karachi", NOT(OR(C1026="Toyota", C1026="Honda"))), "SELECTED", "NOT SELECTED") -> NOT SELECTED | N1026: =LEN(D1026) -> 14 | O1026: =RIGHT(D1026, LEN(D1026) - FIND(" ", D1026)) -> Hijet | P1026: =ROUND((2025-E1026),3) -> 12
A1027: 1078420313 | B1027: Hyundai santro 2007 | C1027: Hyundai | D1027: Hyundai Santro | E1027: 2007 | F1027: 148000 | G1027: 1060000 | H1027: {=VLOOKUP(A1027,Cars_dataset_sheet2!A:I,{2,3,7,8,9},FALSE)} -> Petrol | I1027: Lahore | J1027: Local | K1027: Manual | L1027: Used | M1027: =IF(AND(OR(H1027="Petrol", H1027="CNG"), I1027<>"Karachi", NOT(OR(C1027="Toyota", C1027="Honda"))), "SELECTED", "NOT SELECTED") -> SELECTED | N1027: =LEN(D1027) -> 14 | O1027: =RIGHT(D1027, LEN(D1027) - FIND(" ", D1027)) -> Santro | P1027: =ROUND((2025-E1027),3) -> 18
... A1088: 1078555589 | B1088: Sentro Club (New Engine) | C1088: Hyundai | D1088: Hyundai Santro | E1088: 2005 | F1088: 1000 | G1088: 1040000 | H1088: {=VLOOKUP(A1088,Cars_dataset_sheet2!A:I,{2,3,7,8,9},FALSE)} -> Petrol | I1088: Lahore | J1088: Local | K1088: Manual | L1088: Used | M1088: =IF(AND(OR(H1088="Petrol", H1088="CNG"), I1088<>"Karachi", NOT(OR(C1088="Toyota", C1088="Honda"))), "SELECTED", "NOT SELECTED") -> SELECTED | N1088: =LEN(D1088) -> 14 | O1088: =RIGHT(D1088, LEN(D1088) - FIND(" ", D1088)) -> Santro | P1088: =ROUND((2025-E1088),3) -> 20
A1089: 1078557043 | B1089: 3226934100 | C1089: Daihatsu | D1089: Daihatsu Move | E1089: 2018 | F1089: 130000 | G1089: 2390000 | H1089: {=VLOOKUP(A1089,Cars_dataset_sheet2!A:I,{2,3,7,8,9},FALSE)} -> Petrol | I1089: Lahore | J1089: Imported | K1089: Automatic | L1089: Used | M1089: =IF(AND(OR(H1089="Petrol", H1089="CNG"), I1089<>"Karachi", NOT(OR(C1089="Toyota", C1089="Honda"))), "SELECTED", "NOT SELECTED") -> SELECTED | N1089: =LEN(D1089) -> 13 | O1089: =RIGHT(D1089, LEN(D1089) - FIND(" ", D1089)) -> Move | P1089: =ROUND((2025-E1089),3) -> 7
A1090: 1078562919 | B1090: Toyota Passo 2014/2016 | C1090: Toyota | D1090: Toyota Passo | E1090: 2014 | F1090: 69000 | G1090: 2530000 | H1090: {=VLOOKUP(A1090,Cars_dataset_sheet2!A:I,{2,3,7,8,9},FALSE)} -> Petrol | I1090: Karachi | J1090: Imported | K1090: Automatic | L1090: Used | M1090: =IF(AND(OR(H1090="Petrol", H1090="CNG"), I1090<>"Karachi", NOT(OR(C1090="Toyota", C1090="Honda"))), "SELECTED", "NOT SELECTED") -> NOT SELECTED | N1090: =LEN(D1090) -> 12 | O1090: =RIGHT(D1090, LEN(D1090) - FIND(" ", D1090)) -> Passo | P1090: =ROUND((2025-E1090),3) -> 11
A1091: 1078563475 | B1091: Suzuki Mahran | C1091: Suzuki | D1091: Suzuki Mehran VXR | E1091: 2007 | F1091: 82820 | G1091: 700000 | H1091: {=VLOOKUP(A1091,Cars_dataset_sheet2!A:I,{2,3,7,8,9},FALSE)} -> CNG | I1091: Lahore | J1091: Local | K1091: Manual | L1091: Used | M1091: =IF(AND(OR(H1091="Petrol", H1091="CNG"), I1091<>"Karachi", NOT(OR(C1091="Toyota", C1091="Honda"))), "SELECTED", "NOT SELECTED") -> SELECTED | N1091: =LEN(D1091) -> 17 | O1091: =RIGHT(D1091, LEN(D1091) - FIND(" ", D1091)) -> Mehran VXR | P1091: =ROUND((2025-E1091),3) -> 18
A1092: 1078563817 | B1092: gli 2017/18 white totally genuine except one and half door | C1092: Toyota | D1092: Toyota Corolla GLI | E1092: 2018 | F1092: 95000 | G1092: 3995000 | H1092: {=VLOOKUP(A1092,Cars_dataset_sheet2!A:I,{2,3,7,8,9},FALSE)} -> Petrol | I1092: Lahore | J1092: Local | K1092: Manual | L1092: Used | M1092: =IF(AND(OR(H1092="Petrol", H1092="CNG"), I1092<>"Karachi", NOT(OR(C1092="Toyota", C1092="Honda"))), "SELECTED", "NOT SELECTED") -> NOT SELECTED | N1092: =LEN(D1092) -> 18 | O1092: =RIGHT(D1092, LEN(D1092) - FIND(" ", D1092)) -> Corolla GLI | P1092: =ROUND((2025-E1092),3) -> 7
A1093: 1078565376 | B1093: Suzuki Ravi 2007 | C1093: Suzuki | D1093: Suzuki Ravi | E1093: 2007 | F1093: 40000 | G1093: 700000 | H1093: {=VLOOKUP(A1093,Cars_dataset_sheet2!A:I,{2,3,7,8,9},FALSE)} -> Petrol | I1093: Karachi | J1093: Local | K1093: Manual | L1093: Used | M1093: =IF(AND(OR(H1093="Petrol", H1093="CNG"), I1093<>"Karachi", NOT(OR(C1093="Toyota", C1093="Honda"))), "SELECTED", "NOT SELECTED") -> NOT SELECTED | N1093: =LEN(D1093) -> 11 | O1093: =RIGHT(D1093, LEN(D1093) - FIND(" ", D1093)) -> Ravi | P1093: =ROUND((2025-E1093),3) -> 18
A1094: 1078578893 | B1094: final price | C1094: Suzuki | D1094: Suzuki Swift | E1094: 2020 | F1094: 75000 | G1094: 2450000 | H1094: {=VLOOKUP(A1094,Cars_dataset_sheet2!A:I,{2,3,7,8,9},FALSE)} -> Petrol | I1094: Islamabad | J1094: Local | K1094: Manual | L1094: Used | M1094: =IF(AND(OR(H1094="Petrol", H1094="CNG"), I1094<>"Karachi", NOT(OR(C1094="Toyota", C1094="Honda"))), "SELECTED", "NOT SELECTED") -> SELECTED | N1094: =LEN(D1094) -> 12 | O1094: =RIGHT(D1094, LEN(D1094) - FIND(" ", D1094)) -> Swift | P1094: =ROUND((2025-E1094),3) -> 5
A1095: 1078580569 | B1095: Suzuki Wagonr vxl 2018 | C1095: Suzuki | D1095: Suzuki Wagon R | E1095: 2018 | F1095: 68000 | G1095: 1925000 | H1095: {=VLOOKUP(A1095,Cars_dataset_sheet2!A:I,{2,3,7,8,9},FALSE)} -> Petrol | I1095: Karachi | J1095: Local | K1095: Manual | L1095: Used | M1095: =IF(AND(OR(H1095="Petrol", H1095="CNG"), I1095<>"Karachi", NOT(OR(C1095="Toyota", C1095="Honda"))), "SELECTED", "NOT SELECTED") -> NOT SELECTED | N1095: =LEN(D1095) -> 14 | O1095: =RIGHT(D1095, LEN(D1095) - FIND(" ", D1095)) -> Wagon R | P1095: =ROUND((2025-E1095),3) -> 7
A1096: 1078582101 | B1096: suzuki baleno jxr | C1096: Suzuki | D1096: Suzuki Baleno | E1096: 2004 | F1096: 12345 | G1096: 1500000 | H1096: {=VLOOKUP(A1096,Cars_dataset_sheet2!A:I,{2,3,7,8,9},FALSE)} -> Petrol | I1096: Karachi | J1096: Local | K1096: Manual | L1096: Used | M1096: =IF(AND(OR(H1096="Petrol", H1096="CNG"), I1096<>"Karachi", NOT(OR(C1096="Toyota", C1096="Honda"))), "SELECTED", "NOT SELECTED") -> NOT SELECTED | N1096: =LEN(D1096) -> 13 | O1096: =RIGHT(D1096, LEN(D1096) - FIND(" ", D1096)) -> Baleno | P1096: =ROUND((2025-E1096),3) -> 21
A1097: 1078585555 | B1097: 2021 kia picanto low milage the pictures provided are genuine. | C1097: KIA | D1097: KIA Picanto | E1097: 2021 | F1097: 23000 | G1097: 2800000 | H1097: {=VLOOKUP(A1097,Cars_dataset_sheet2!A:I,{2,3,7,8,9},FALSE)} -> Petrol | I1097: Karachi | J1097: Imported | K1097: Automatic | L1097: Used | M1097: =IF(AND(OR(H1097="Petrol", H1097="CNG"), I1097<>"Karachi", NOT(OR(C1097="Toyota", C1097="Honda"))), "SELECTED", "NOT SELECTED") -> NOT SELECTED | N1097: =LEN(D1097) -> 11 | O1097: =RIGHT(D1097, LEN(D1097) - FIND(" ", D1097)) -> Picanto | P1097: =ROUND((2025-E1097),3) -> 4
A1098: 1078586269 | B1098: Yaris | C1098: Toyota | D1098: Toyota Yaris | E1098: 2021 | F1098: 40000 | G1098: 4600000 | H1098: {=VLOOKUP(A1098,Cars_dataset_sheet2!A:I,{2,3,7,8,9},FALSE)} -> Petrol | I1098: Karachi | J1098: Local | K1098: Automatic | L1098: Used | M1098: =IF(AND(OR(H1098="Petrol", H1098="CNG"), I1098<>"Karachi", NOT(OR(C1098="Toyota", C1098="Honda"))), "SELECTED", "NOT SELECTED") -> NOT SELECTED | N1098: =LEN(D1098) -> 12 | O1098: =RIGHT(D1098, LEN(D1098) - FIND(" ", D1098)) -> Yaris | P1098: =ROUND((2025-E1098),3) -> 4
A1099: 1078587840 | B1099: corolla GLI 2020 | C1099: Toyota | D1099: Toyota Corolla GLI | E1099: 2020 | F1099: 140000 | G1099: 4500000 | H1099: {=VLOOKUP(A1099,Cars_dataset_sheet2!A:I,{2,3,7,8,9},FALSE)} -> Petrol | I1099: Lahore | J1099: Imported | K1099: Automatic | L1099: Used | M1099: =IF(AND(OR(H1099="Petrol", H1099="CNG"), I1099<>"Karachi", NOT(OR(C1099="Toyota", C1099="Honda"))), "SELECTED", "NOT SELECTED") -> NOT SELECTED | N1099: =LEN(D1099) -> 18 | O1099: =RIGHT(D1099, LEN(D1099) - FIND(" ", D1099)) -> Corolla GLI | P1099: =ROUND((2025-E1099),3) -> 5
A1100: 1078594006 | B1100: terios kid | C1100: Daihatsu | D1100: Daihatsu Terios Kid | E1100: 2004 | F1100: 123123 | G1100: 1425000 | H1100: {=VLOOKUP(A1100,Cars_dataset_sheet2!A:I,{2,3,7,8,9},FALSE)} -> Petrol | I1100: Sialkot | J1100: Imported | K1100: Automatic | L1100: Used | M1100: =IF(AND(OR(H1100="Petrol", H1100="CNG"), I1100<>"Karachi", NOT(OR(C1100="Toyota", C1100="Honda"))), "SELECTED", "NOT SELECTED") -> SELECTED | N1100: =LEN(D1100) -> 19 | O1100: =RIGHT(D1100, LEN(D1100) - FIND(" ", D1100)) -> Terios Kid | P1100: =ROUND((2025-E1100),3) -> 21
A1101: 1078594500 | B1101: Honda Civic 2016Model Oriel | C1101: Honda | D1101: Honda Civic Oriel | E1101: 2016 | F1101: 116000 | G1101: 4550000 | H1101: {=VLOOKUP(A1101,Cars_dataset_sheet2!A:I,{2,3,7,8,9},FALSE)} -> Petrol | I1101: Lahore | J1101: Local | K1101: Automatic | L1101: Used | M1101: =IF(AND(OR(H1101="Petrol", H1101="CNG"), I1101<>"Karachi", NOT(OR(C1101="Toyota", C1101="Honda"))), "SELECTED", "NOT SELECTED") -> NOT SELECTED | N1101: =LEN(D1101) -> 17 | O1101: =RIGHT(D1101, LEN(D1101) - FIND(" ", D1101)) -> Civic Oriel | P1101: =ROUND((2025-E1101),3) -> 9
... A1597: 1079292907 | B1597: KIA Picanto | C1597: KIA | D1597: KIA Picanto | E1597: 2021 | F1597: 43000 | G1597: 2975000 | H1597: {=VLOOKUP(A1597,Cars_dataset_sheet2!A:I,{2,3,7,8,9},FALSE)} -> Petrol | I1597: Karachi | J1597: Local | K1597: Automatic | L1597: Used | M1597: =IF(AND(OR(H1597="Petrol", H1597="CNG"), I1597<>"Karachi", NOT(OR(C1597="Toyota", C1597="Honda"))), "SELECTED", "NOT SELECTED") -> NOT SELECTED | N1597: =LEN(D1597) -> 11 | O1597: =RIGHT(D1597, LEN(D1597) - FIND(" ", D1597)) -> Picanto | P1597: =ROUND((2025-E1597),3) -> 4
A1598: 1079293060 | B1598: 3344040213 | C1598: Toyota | D1598: Toyota Corolla XLI | E1598: 2005 | F1598: 195000 | G1598: 1350000 | H1598: {=VLOOKUP(A1598,Cars_dataset_sheet2!A:I,{2,3,7,8,9},FALSE)} -> Petrol | I1598: Lahore | J1598: Local | K1598: Manual | L1598: Used | M1598: =IF(AND(OR(H1598="Petrol", H1598="CNG"), I1598<>"Karachi", NOT(OR(C1598="Toyota", C1598="Honda"))), "SELECTED", "NOT SELECTED") -> NOT SELECTED | N1598: =LEN(D1598) -> 18 | O1598: =RIGHT(D1598, LEN(D1598) - FIND(" ", D1598)) -> Corolla XLI | P1598: =ROUND((2025-E1598),3) -> 20
A1599: 1079293250 | B1599: Mehran VXR 2019 | C1599: Suzuki | D1599: Suzuki Mehran VXR | E1599: 2019 | F1599: 47000 | G1599: 1850000 | H1599: {=VLOOKUP(A1599,Cars_dataset_sheet2!A:I,{2,3,7,8,9},FALSE)} -> Petrol | I1599: Rawalpindi | J1599: Local | K1599: Manual | L1599: Used | M1599: =IF(AND(OR(H1599="Petrol", H1599="CNG"), I1599<>"Karachi", NOT(OR(C1599="Toyota", C1599="Honda"))), "SELECTED", "NOT SELECTED") -> SELECTED | N1599: =LEN(D1599) -> 17 | O1599: =RIGHT(D1599, LEN(D1599) - FIND(" ", D1599)) -> Mehran VXR | P1599: =ROUND((2025-E1599),3) -> 6
A1600: 1079294931 | B1600: Mehran car vxr 2012 | C1600: Suzuki | D1600: Suzuki Mehran VXR | E1600: 2012 | F1600: 190000 | G1600: 620000 | H1600: {=VLOOKUP(A1600,Cars_dataset_sheet2!A:I,{2,3,7,8,9},FALSE)} -> Petrol | I1600: Vehari | J1600: Local | K1600: Manual | L1600: Used | M1600: =IF(AND(OR(H1600="Petrol", H1600="CNG"), I1600<>"Karachi", NOT(OR(C1600="Toyota", C1600="Honda"))), "SELECTED", "NOT SELECTED") -> SELECTED | N1600: =LEN(D1600) -> 17 | O1600: =RIGHT(D1600, LEN(D1600) - FIND(" ", D1600)) -> Mehran VXR | P1600: =ROUND((2025-E1600),3) -> 13
A1601: 1079294962 | B1601: urgent sale Wagnor vxl 2018 | C1601: Suzuki | D1601: Suzuki Wagon R | E1601: 2018 | F1601: 66000 | G1601: 2150000 | H1601: {=VLOOKUP(A1601,Cars_dataset_sheet2!A:I,{2,3,7,8,9},FALSE)} -> Petrol | I1601: Lahore | J1601: Imported | K1601: Manual | L1601: Used | M1601: =IF(AND(OR(H1601="Petrol", H1601="CNG"), I1601<>"Karachi", NOT(OR(C1601="Toyota", C1601="Honda"))), "SELECTED", "NOT SELECTED") -> SELECTED | N1601: =LEN(D1601) -> 14 | O1601: =RIGHT(D1601, LEN(D1601) - FIND(" ", D1601)) -> Wagon R | P1601: =ROUND((2025-E1601),3) -> 7
A1602: 1079295542 | B1602: Lahore Number Gari ki condition bht achi ha Drive smooth AC Chill | C1602: Mitsubishi | D1602: Mitsubishi Lancer | E1602: 2005 | F1602: 180000 | G1602: 1220000 | H1602: {=VLOOKUP(A1602,Cars_dataset_sheet2!A:I,{2,3,7,8,9},FALSE)} -> Petrol | I1602: Sahiwal | J1602: Imported | K1602: Manual | L1602: Used | M1602: =IF(AND(OR(H1602="Petrol", H1602="CNG"), I1602<>"Karachi", NOT(OR(C1602="Toyota", C1602="Honda"))), "SELECTED", "NOT SELECTED") -> SELECTED | N1602: =LEN(D1602) -> 17 | O1602: =RIGHT(D1602, LEN(D1602) - FIND(" ", D1602)) -> Lancer | P1602: =ROUND((2025-E1602),3) -> 20
A1603: 1079296103 | B1603: Suzuki Mehran Vxr | C1603: Suzuki | D1603: Suzuki Mehran VXR | E1603: 2017 | F1603: 86000 | G1603: 1315000 | H1603: {=VLOOKUP(A1603,Cars_dataset_sheet2!A:I,{2,3,7,8,9},FALSE)} -> Petrol | I1603: Faisalabad | J1603: Local | K1603: Manual | L1603: Used | M1603: =IF(AND(OR(H1603="Petrol", H1603="CNG"), I1603<>"Karachi", NOT(OR(C1603="Toyota", C1603="Honda"))), "SELECTED", "NOT SELECTED") -> SELECTED | N1603: =LEN(D1603) -> 17 | O1603: =RIGHT(D1603, LEN(D1603) - FIND(" ", D1603)) -> Mehran VXR | P1603: =ROUND((2025-E1603),3) -> 8
A1604: 1079296505 | B1604: mehran vxr 2017 model. genuine car no shower | C1604: Suzuki | D1604: Suzuki Mehran VXR | E1604: 2017 | F1604: 85000 | G1604: 1200000 | H1604: {=VLOOKUP(A1604,Cars_dataset_sheet2!A:I,{2,3,7,8,9},FALSE)} -> Petrol | I1604: Lahore | J1604: Local | K1604: Manual | L1604: Used | M1604: =IF(AND(OR(H1604="Petrol", H1604="CNG"), I1604<>"Karachi", NOT(OR(C1604="Toyota", C1604="Honda"))), "SELECTED", "NOT SELECTED") -> SELECTED | N1604: =LEN(D1604) -> 17 | O1604: =RIGHT(D1604, LEN(D1604) - FIND(" ", D1604)) -> Mehran VXR | P1604: =ROUND((2025-E1604),3) -> 8
A1605: 1079298574 | B1605: Honda City Aspire 1.5 New Shape Isb Reg. (2022) | C1605: Honda | D1605: Honda City Aspire | E1605: 2021 | F1605: 25000 | G1605: 5000000 | H1605: {=VLOOKUP(A1605,Cars_dataset_sheet2!A:I,{2,3,7,8,9},FALSE)} -> Petrol | I1605: Islamabad | J1605: Local | K1605: Automatic | L1605: Used | M1605: =IF(AND(OR(H1605="Petrol", H1605="CNG"), I1605<>"Karachi", NOT(OR(C1605="Toyota", C1605="Honda"))), "SELECTED", "NOT SELECTED") -> NOT SELECTED | N1605: =LEN(D1605) -> 17 | O1605: =RIGHT(D1605, LEN(D1605) - FIND(" ", D1605)) -> City Aspire | P1605: =ROUND((2025-E1605),3) -> 4
A1606: 1079299769 | B1606: suzuki bolan kohat. whattsapp plz | C1606: Suzuki | D1606: Suzuki Bolan | E1606: 2021 | F1606: 30000 | G1606: 1920000 | H1606: {=VLOOKUP(A1606,Cars_dataset_sheet2!A:I,{2,3,7,8,9},FALSE)} -> Petrol | I1606: Islamabad | J1606: Local | K1606: Manual | L1606: Used | M1606: =IF(AND(OR(H1606="Petrol", H1606="CNG"), I1606<>"Karachi", NOT(OR(C1606="Toyota", C1606="Honda"))), "SELECTED", "NOT SELECTED") -> SELECTED | N1606: =LEN(D1606) -> 12 | O1606: =RIGHT(D1606, LEN(D1606) - FIND(" ", D1606)) -> Bolan | P1606: =ROUND((2025-E1606),3) -> 4
A1607: 1079304641 | B1607: Mercedes E200 2003/2006 | C1607: Mercedes | D1607: Mercedes E Class | E1607: 2003 | F1607: 107000 | G1607: 4500000 | H1607: {=VLOOKUP(A1607,Cars_dataset_sheet2!A:I,{2,3,7,8,9},FALSE)} -> Petrol | I1607: Karachi | J1607: Imported | K1607: Automatic | L1607: Used | M1607: =IF(AND(OR(H1607="Petrol", H1607="CNG"), I1607<>"Karachi", NOT(OR(C1607="Toyota", C1607="Honda"))), "SELECTED", "NOT SELECTED") -> NOT SELECTED | N1607: =LEN(D1607) -> 16 | O1607: =RIGHT(D1607, LEN(D1607) - FIND(" ", D1607)) -> E Class | P1607: =ROUND((2025-E1607),3) -> 22
A1608: 1079305170 | B1608: Toyota Corolla GLi Automatic 1.3 VVTi | C1608: Toyota | D1608: Toyota Corolla GLI | E1608: 2017 | F1608: 111000 | G1608: 4100000 | H1608: {=VLOOKUP(A1608,Cars_dataset_sheet2!A:I,{2,3,7,8,9},FALSE)} -> Petrol | I1608: Rawalpindi | J1608: Local | K1608: Automatic | L1608: Used | M1608: =IF(AND(OR(H1608="Petrol", H1608="CNG"), I1608<>"Karachi", NOT(OR(C1608="Toyota", C1608="Honda"))), "SELECTED", "NOT SELECTED") -> NOT SELECTED | N1608: =LEN(D1608) -> 18 | O1608: =RIGHT(D1608, LEN(D1608) - FIND(" ", D1608)) -> Corolla GLI | P1608: =ROUND((2025-E1608),3) -> 8
A1609: 1079307483 | B1609: Daihatsu Mira 2012 | C1609: Daihatsu | D1609: Daihatsu Mira | E1609: 2012 | F1609: 45000 | G1609: 800000 | H1609: {=VLOOKUP(A1609,Cars_dataset_sheet2!A:I,{2,3,7,8,9},FALSE)} -> Petrol | I1609: Karachi | J1609: Imported | K1609: Automatic | L1609: Used | M1609: =IF(AND(OR(H1609="Petrol", H1609="CNG"), I1609<>"Karachi", NOT(OR(C1609="Toyota", C1609="Honda"))), "SELECTED", "NOT SELECTED") -> NOT SELECTED | N1609: =LEN(D1609) -> 13 | O1609: =RIGHT(D1609, LEN(D1609) - FIND(" ", D1609)) -> Mira | P1609: =ROUND((2025-E1609),3) -> 13
A1610: 1079307682 | B1610: 2015 import | C1610: Suzuki | D1610: Suzuki Wagon R | E1610: 2015 | F1610: 85000 | G1610: 2300000 | H1610: {=VLOOKUP(A1610,Cars_dataset_sheet2!A:I,{2,3,7,8,9},FALSE)} -> Petrol | I1610: Sindh | J1610: Imported | K1610: Automatic | L1610: Used | M1610: =IF(AND(OR(H1610="Petrol", H1610="CNG"), I1610<>"Karachi", NOT(OR(C1610="Toyota", C1610="Honda"))), "SELECTED", "NOT SELECTED") -> SELECTED | N1610: =LEN(D1610) -> 14 | O1610: =RIGHT(D1610, LEN(D1610) - FIND(" ", D1610)) -> Wagon R | P1610: =ROUND((2025-E1610),3) -> 10
... A1658: 1079343718 | B1658: Toyota Corolla xli total genuine Karachi registered ( 033319 47927 ) | C1658: Toyota | D1658: Toyota Corolla XLI | E1658: 2015 | F1658: 148537 | G1658: 2960000 | H1658: {=VLOOKUP(A1658,Cars_dataset_sheet2!A:I,{2,3,7,8,9},FALSE)} -> Petrol | I1658: Karachi | J1658: Local | K1658: Manual | L1658: Used | M1658: =IF(AND(OR(H1658="Petrol", H1658="CNG"), I1658<>"Karachi", NOT(OR(C1658="Toyota", C1658="Honda"))), "SELECTED", "NOT SELECTED") -> NOT SELECTED | N1658: =LEN(D1658) -> 18 | O1658: =RIGHT(D1658, LEN(D1658) - FIND(" ", D1658)) -> Corolla XLI | P1658: =ROUND((2025-E1658),3) -> 10
A1659: 1079344053 | B1659: 3000664041 | C1659: Hyundai | D1659: Hyundai Santro | E1659: 2000 | F1659: 190000 | G1659: 600000 | H1659: {=VLOOKUP(A1659,Cars_dataset_sheet2!A:I,{2,3,7,8,9},FALSE)} -> Petrol | I1659: Karachi | J1659: Imported | K1659: Manual | L1659: Used | M1659: =IF(AND(OR(H1659="Petrol", H1659="CNG"), I1659<>"Karachi", NOT(OR(C1659="Toyota", C1659="Honda"))), "SELECTED", "NOT SELECTED") -> NOT SELECTED | N1659: =LEN(D1659) -> 14 | O1659: =RIGHT(D1659, LEN(D1659) - FIND(" ", D1659)) -> Santro | P1659: =ROUND((2025-E1659),3) -> 25
...

Sheet Question Answers
A2: Answer no 1 | E2: Answer no 2 | I2: Answer no 3 | M2: Answer no 4 | S2: Answer no 5
A4: Make | B4: Suzuki | E4: Make | F4: Honda | I4: Registration_city | J4: Karachi | M4: Count of Ad ID | N4: Column Labels | S4: Count of Ad ID | T4: Column Labels
E5: Transmission | F5: Automatic | I5: Assembly | J5: Imported | M5: Row Labels | N5: Automatic | O5: Manual | P5: Grand Total | S5: Row Labels | T5: Imported | U5: Local | V5: Grand Total
A6: Row Labels | B6: Average of Price | E6: Assembly | F6: Local | M6: Abbottabad | N6: 0 | O6: 1 | P6: 1 | S6: Abbottabad | T6: 0 | U6: 0.0004456328 | V6: 0.0004456328
A7: Alto | B7: 1565165.5 | I7: Row Labels | J7: Max of Price | M7: Arifwala | N7: 0 | O7: 1 | P7: 1 | S7: Arifwala | T7: 0.0001114082 | U7: 0 | V7: 0.0001114082
A8: Baleno | B8: 909113.62 | E8: Row Labels | F8: Count of Ad ID | I8: Changan | J8: 3900000 | M8: Attock | N8: 0 | O8: 1 | P8: 1 | S8: Attock | T8: 0.0002228164 | U8: 0.0001114082 | V8: 0.0003342246
A9: Bolan | B9: 1021034.8 | E9: Bahawalpur | F9: 1 | I9: Chevrolet | J9: 1050000 | M9: Badin | N9: 1 | O9: 0 | P9: 1 | S9: Badin | T9: 0.0001114082 | U9: 0 | V9: 0.0001114082
A10: Cervo | B10: 1345000 | E10: Bannu | F10: 1 | I10: Daihatsu | J10: 4080000 | M10: Bahawalnagar | N10: 0 | O10: 1 | P10: 1 | S10: Bahawalnagar | T10: 0 | U10: 0.0001114082 | V10: 0.0001114082
A11: Cultus VXL | B11: 650000 | E11: Faisalabad | F11: 7 | I11: FAW | J11: 1500000 | M11: Bahawalpur | N11: 0.22222222 | O11: 0.77777778 | P11: 1 | S11: Bahawalpur | T11: 0.0002228164 | U11: 0.0017825312 | V11: 0.0020053476
A12: Cultus VXR | B12: 1198606.7 | E12: Gujranwala | F12: 1 | I12: Honda | J12: 4600000 | M12: Bannu | N12: 1 | O12: 0 | P12: 1 | S12: Bannu | T12: 0 | U12: 0.0002228164 | V12: 0.0002228164
A13: Every | B13: 1767351.2 | E13: Gujrat | F13: 1 | I13: Hyundai | J13: 1000000 | M13: Bhakkar | N13: 0 | O13: 1 | P13: 1 | S13: Bhakkar | T13: 0 | U13: 0.0001114082 | V13: 0.0001114082
A14: Every Wagon | B14: 2275000 | E14: Islamabad | F14: 100 | I14: KIA | J14: 3350000 | M14: Bhimber | N14: 0 | O14: 1 | P14: 1 | S14: Bhimber | T14: 0 | U14: 0.0001114082 | V14: 0.0001114082
A15: Khyber | B15: 185000 | E15: Karachi | F15: 227 | I15: Mercedes | J15: 4600000 | M15: Charsadda | N15: 0 | O15: 1 | P15: 1 | S15: Charsadda | T15: 0 | U15: 0.0001114082 | V15: 0.0001114082
A16: Liana | B16: 1250000 | E16: Lahore | F16: 304 | I16: Mitsubishi | J16: 3200000 | M16: Chiniot | N16: 0 | O16: 1 | P16: 1 | S16: Chiniot | T16: 0.0001114082 | U16: 0.0001114082 | V16: 0.0002228164
A17: Mehran VX | B17: 842500 | E17: Multan | F17: 4 | I17: Suzuki | J17: 2800000 | M17: Chishtian Mandi | N17: 0 | O17: 1 | P17: 1 | S17: Chishtian Mandi | T17: 0 | U17: 0.0001114082 | V17: 0.0001114082
A18: Mehran VXR | B18: 902563.22 | E18: Peshawar | F18: 3 | I18: Toyota | J18: 4990000 | M18: Dadu | N18: 0 | O18: 1 | P18: 1 | S18: Dadu | T18: 0 | U18: 0.0001114082 | V18: 0.0001114082
A19: Ravi | B19: 984296.3 | E19: Punjab | F19: 28 | I19: Grand Total | J19: 4990000 | M19: Dera Ghazi Khan | N19: 0.25 | O19: 0.75 | P19: 1 | S19: Dera Ghazi Khan | T19: 0.0002228164 | U19: 0.0002228164 | V19: 0.0004456328
A20: Swift | B20: 2427501.7 | E20: Rawalpindi | F20: 2 | M20: Dera Ismail Khan | N20: 0 | O20: 1 | P20: 1 | S20: Dera Ismail Khan | T20: 0.0001114082 | U20: 0 | V20: 0.0001114082
A21: Wagon R | B21: 2290678.5 | E21: Sahiwal | F21: 1 | M21: Faisalabad | N21: 0.14814815 | O21: 0.85185185 | P21: 1 | S21: Faisalabad | T21: 0.006684492 | U21: 0.014371658 | V21: 0.02105615
A22: Grand Total | B22: 1482622.5 | E22: Sialkot | F22: 5 | M22: Gujranwala | N22: 0.16129032 | O22: 0.83870968 | P22: 1 | S22: Gujranwala | T22: 0.001114082 | U22: 0.0023395722 | V22: 0.0034536542
E23: Sindh | F23: 45 | M23: Gujrat | N23: 0.25 | O23: 0.75 | P23: 1 | S23: Gujrat | T23: 0.0002228164 | U23: 0.0006684492 | V23: 0.0008912656
E24: Unregistered | F24: 1 | M24: Hafizabad | N24: 0 | O24: 1 | P24: 1 | S24: Hafizabad | T24: 0.0001114082 | U24: 0 | V24: 0.0001114082
E25: Grand Total | F25: 731 | M25: Haripur | N25: 0 | O25: 1 | P25: 1 | S25: Haripur | T25: 0.0001114082 | U25: 0 | V25: 0.0001114082
M26: Hyderabad | N26: 0.30769231 | O26: 0.69230769 | P26: 1 | S26: Hyderabad | T26: 0.001114082 | U26: 0.0017825312 | V26: 0.0028966132
M27: Islamabad | N27: 0.44226044 | O27: 0.55773956 | P27: 1 | S27: Islamabad | T27: 0.045231729 | U27: 0.090797683 | V27: 0.13602941
M28: Jaranwala | N28: 0 | O28: 1 | P28: 1 | S28: Jaranwala | T28: 0.0001114082 | U28: 0 | V28: 0.0001114082
M29: Jhang Sadar | N29: 0.25 | O29: 0.75 | P29: 1 | S29: Jhang Sadar | T29: 0.0001114082 | U29: 0.0003342246 | V29: 0.0004456328
M30: Jhelum | N30: 0 | O30: 1 | P30: 1 | S30: Jhelum | T30: 0.0003342246 | U30: 0.0007798574 | V30: 0.001114082
M31: Karachi | N31: 0.47801578 | O31: 0.52198422 | P31: 1 | S31: Karachi | T31: 0.11096257 | U31: 0.18549465 | V31: 0.29645722
M32: Kasur | N32: 0 | O32: 1 | P32: 1 | S32: Kasur | T32: 0.0001114082 | U32: 0.0002228164 | V32: 0.0003342246
M33: Khanewal | N33: 0.25 | O33: 0.75 | P33: 1 | S33: Khanewal | T33: 0.0001114082 | U33: 0.0003342246 | V33: 0.0004456328
M34: Khanpur | N34: 0 | O34: 1 | P34: 1 | S34: Khanpur | T34: 0.0001114082 | U34: 0 | V34: 0.0001114082
M35: Khushab | N35: 0 | O35: 1 | P35: 1 | S35: Khushab | T35: 0.0001114082 | U35: 0 | V35: 0.0001114082
M36: Lahore | N36: 0.32374741 | O36: 0.67625259 | P36: 1 | S36: Lahore | T36: 0.1208779 | U36: 0.25490196 | V36: 0.37577986
M37: Larkana | N37: 0.33333333 | O37: 0.66666667 | P37: 1 | S37: Larkana | T37: 0.0001114082 | U37: 0.0002228164 | V37: 0.0003342246
... M67: Grand Total | N67: 0.38836898 | O67: 0.61163102 | P67: 1 | S67: Grand Total | T67: 0.34803922 | U67: 0.65196078 | V67: 1
